Workbook

Sheet Raw_Data
A1: RAW DATA — 120 Transaction Records | Contains Intentional Errors
A2: Transaction ID | B2: Date | C2: Customer Name | D2: Product | E2: Quantity | F2: Unit Price ($) | G2: Total Amount ($) | H2: Payment Status
A3: TXN1081 | B3: 45376 | C3: Eta Partners | D3: Tablet | E3: 10 | F3: 32000 | G3: 320000 | H3: Refunded
A4: TXN1082 | B4: 45402 | C4: Nu Ventures | D4: Printer | E4: 17 | F4: 18000 | G4: 306000 | H4: Paid
A5: TXN1083 | B5: 45550 | C5: Iota Ltd | D5: Mouse | E5: 1 | F5: 1200 | G5: 1320 | H5: Pending
A6: TXN1020 | B6: 45511 | C6: Beta Ltd | D6: Keyboard | E6: 8 | F6: 3500 | G6: 28000 | H6: Paid
A7: TXN1085 | B7: 45647 | C7: Acme Corp | D7: Tablet | E7: 14 | F7: 32000 | G7: 448000 | H7: Refunded
A8: TXN1086 | B8: 45309 | C8: Zeta Group | D8: Scanner | E8: 16 | F8: 12000 | G8: 192000 | H8: Paid
A9: TXN1087 | B9: 45624 | C9: [BLANK] | D9: Webcam | E9: 1 | F9: 4500 | G9: 4500 | H9: Paid
A10: TXN1088 | B10: 45337 | C10: Beta Ltd | D10: Laptop | E10: 15 | F10: 85000 | G10: 1275000 | H10: Paid
A11: TXN1020 | B11: 45467 | C11: Eta Partners | D11: Printer | E11: 5 | F11: 18000 | G11: 90000 | H11: Paid
A12: TXN1090 | B12: 45632 | C12: Acme Corp | D12: Printer | E12: 8 | F12: 18000 | G12: 144000 | H12: Paid
A13: TXN1091 | B13: 45393 | C13: Delta Co | D13: USB Hub | E13: 3 | F13: 2200 | G13: 7260 | H13: Refunded
A14: TXN1092 | B14: 45578 | C14: Xi Corp | D14: [BLANK] | E14: 13 | F14: 5000 | G14: 65000 | H14: Paid
... A23: TXN1101 | B23: 45511 | C23: Zeta Group | D23: Keyboard | E23: 2 | F23: 3500 | G23: 7000 | H23: Paid
A24: TXN1102 | C24: Eta Partners | D24: Keyboard | E24: 19 | F24: 3500 | G24: 66500 | H24: Paid
A25: TXN1103 | B25: 45469 | C25: Theta Corp | D25: Scanner | E25: 13 | F25: 12000 | G25: 156000 | H25: Paid
A26: TXN1005 | B26: 45375 | C26: Iota Ltd | D26: Monitor | E26: 15 | F26: 22000 | G26: 330000 | H26: Failed
A27: TXN1105 | B27: 45539 | C27: Acme Corp | D27: Headphones | E27: 2 | F27: 8500 | G27: 17000 | H27: Pending
A28: TXN1106 | B28: 45629 | C28: Epsilon LLC | D28: Laptop | E28: 14 | F28: 85000 | G28: 1190000 | H28: Paid
A29: TXN1107 | B29: 45379 | C29: [BLANK] | D29: Tablet | E29: 3 | F29: 32000 | G29: 144000 | H29: Paid
A30: TXN1108 | B30: 45369 | C30: Mu Holdings | D30: Printer | E30: 2 | F30: 18000 | G30: 36000 | H30: Pending
A31: TXN1005 | B31: 45624 | C31: Iota Ltd | D31: Printer | E31: 1 | F31: 18000 | G31: 18000 | H31: Paid
A32: TXN1110 | B32: 45479 | C32: Nu Ventures | D32: Keyboard | E32: 12 | F32: 3500 | G32: 42000 | H32: Failed
A33: TXN1111 | B33: 45540 | C33: Kappa Inc | D33: Printer | E33: 10 | F33: 18000 | G33: 180000 | H33: Paid
A34: TXN1112 | B34: 45565 | C34: Kappa Inc | D34: [BLANK] | E34: 9 | F34: 5000 | G34: 45000 | H34: Paid
A35: TXN1113 | B35: 45297 | C35: Eta Partners | D35: Keyboard | E35: 1 | F35: 3500 | G35: 3500 | H35: Pending
A36: TXN1020 | B36: 45458 | C36: Lambda Co | D36: Mouse | E36: 19 | F36: 1200 | G36: 22800 | H36: Failed
... A43: TXN1121 | B43: 45601 | C43: Mu Holdings | D43: Scanner | E43: 2 | F43: 12000 | G43: 24000 | H43: Paid
A44: TXN1122 | C44: Eta Partners | D44: Printer | E44: 3 | F44: 18000 | G44: 54000 | H44: Failed
A45: TXN1123 | B45: 45582 | C45: Gamma Inc | D45: Mouse | E45: 9 | F45: 1200 | G45: 13500 | H45: Pending
A46: TXN1001 | B46: 45417 | C46: Eta Partners | D46: Keyboard | E46: 10 | F46: 3500 | G46: 35000 | H46: Pending
A47: TXN1125 | B47: 45549 | C47: Nu Ventures | D47: Scanner | E47: -16 | F47: 12000 | G47: -192000 | H47: Paid
A48: TXN1126 | B48: 45571 | C48: Kappa Inc | D48: Laptop | E48: 17 | F48: 85000 | G48: 1445000 | H48: Pending
A49: TXN1127 | B49: 45556 | C49: [BLANK] | D49: Headphones | E49: 10 | F49: 8500 | G49: 85000 | H49: Paid
A50: TXN1128 | B50: 45324 | C50: Kappa Inc | D50: Webcam | E50: 7 | F50: 4500 | G50: 31500 | H50: Pending
A51: TXN1001 | B51: 45454 | C51: Lambda Co | D51: Tablet | E51: 4 | F51: 32000 | G51: 128000 | H51: Paid
A52: TXN1130 | B52: 45625 | C52: Beta Ltd | D52: Printer | E52: 17 | F52: 18000 | G52: 306000 | H52: Paid
A53: TXN1131 | B53: 45640 | C53: Lambda Co | D53: Printer | E53: 16 | F53: 18000 | G53: 172800 | H53: Failed
A54: TXN1132 | B54: 45497 | C54: Beta Ltd | D54: [BLANK] | E54: 8 | F54: 5000 | G54: 40000 | H54: Paid
A55: TXN1133 | B55: 45316 | C55: Lambda Co | D55: Tablet | E55: 2 | F55: 32000 | G55: 64000 | H55: Paid
A56: TXN1010 | B56: 45652 | C56: Kappa Inc | D56: Tablet | E56: 14 | F56: 32000 | G56: 448000 | H56: Refunded
... A63: TXN1141 | B63: 45395 | C63: Epsilon LLC | D63: Tablet | E63: 5 | F63: 32000 | G63: 160000 | H63: Paid
A64: TXN1142 | C64: Iota Ltd | D64: Keyboard | E64: 3 | F64: 3500 | G64: 10500 | H64: Pending
A65: TXN1143 | B65: 45609 | C65: Eta Partners | D65: Printer | E65: 4 | F65: 18000 | G65: 72000 | H65: Paid
A66: TXN1015 | B66: 45397 | C66: Lambda Co | D66: Webcam | E66: 12 | F66: 4500 | G66: 54000 | H66: Paid
A67: TXN1145 | B67: 45425 | C67: Beta Ltd | D67: Laptop | E67: 11 | F67: 85000 | G67: 935000 | H67: Pending
A68: TXN1146 | B68: 45370 | C68: Omicron Ltd | D68: Scanner | E68: 7 | F68: 12000 | G68: 84000 | H68: Paid
A69: TXN1147 | B69: 45598 | C69: [BLANK] | D69: Headphones | E69: 13 | F69: 8500 | G69: 93925 | H69: Failed
A70: TXN1148 | B70: 45531 | C70: Eta Partners | D70: Tablet | E70: 15 | F70: 32000 | G70: 480000 | H70: Pending
A71: TXN1005 | B71: 45633 | C71: Eta Partners | D71: USB Hub | E71: 9 | F71: 2200 | G71: 19800 | H71: Paid
A72: TXN1150 | B72: 45388 | C72: Delta Co | D72: Laptop | E72: 12 | F72: 85000 | G72: 1020000 | H72: Pending
A73: TXN1151 | B73: 45301 | C73: Beta Ltd | D73: Scanner | E73: 19 | F73: 12000 | G73: 228000 | H73: Paid
A74: TXN1152 | B74: 45495 | C74: Kappa Inc | D74: [BLANK] | E74: 15 | F74: 5000 | G74: 75000 | H74: Refunded
A75: TXN1153 | B75: 45414 | C75: Acme Corp | D75: Scanner | E75: 5 | F75: 12000 | G75: 60000 | H75: Paid
A76: TXN1010 | B76: 45389 | C76: Theta Corp | D76: Webcam | E76: 1 | F76: 4500 | G76: 4500 | H76: Pending
... A83: TXN1161 | B83: 45533 | C83: Lambda Co | D83: Webcam | E83: 5 | F83: 4500 | G83: 22500 | H83: Pending
A84: TXN1162 | C84: Gamma Inc | D84: Webcam | E84: 10 | F84: 4500 | G84: 45000 | H84: Pending
A85: TXN1163 | B85: 45619 | C85: Lambda Co | D85: Laptop | E85: 3 | F85: 85000 | G85: 318750 | H85: Paid
A86: TXN1164 | B86: 45387 | C86: Iota Ltd | D86: Monitor | E86: 7 | F86: 22000 | G86: 154000 | H86: Pending
A87: TXN1165 | B87: 45430 | C87: Zeta Group | D87: Laptop | E87: 6 | F87: 85000 | G87: 510000 | H87: Paid
A88: TXN1166 | B88: 45591 | C88: Theta Corp | D88: Headphones | E88: 13 | F88: 8500 | G88: 110500 | H88: Paid
A89: TXN1167 | B89: 45308 | C89: [BLANK] | D89: Monitor | E89: 8 | F89: 22000 | G89: 176000 | H89: Pending
A90: TXN1168 | B90: 45567 | C90: Epsilon LLC | D90: Tablet | E90: 7 | F90: 32000 | G90: 224000 | H90: Paid
A91: TXN1169 | B91: 45560 | C91: Eta Partners | D91: Monitor | E91: 11 | F91: 0 | G91: 0 | H91: Paid
A92: TXN1170 | B92: 45401 | C92: Iota Ltd | D92: Laptop | E92: 12 | F92: 85000 | G92: 1020000 | H92: Paid
A93: TXN1171 | B93: 45302 | C93: Mu Holdings | D93: Webcam | E93: 16 | F93: 4500 | G93: 144000 | H93: Paid
A94: TXN1172 | B94: 45518 | C94: Nu Ventures | D94: [BLANK] | E94: 1 | F94: 5000 | G94: 5000 | H94: Pending
A95: TXN1173 | B95: 45639 | C95: Acme Corp | D95: Mouse | E95: 20 | F95: 1200 | G95: 24000 | H95: Paid
A96: TXN1174 | B96: 45450 | C96: Eta Partners | D96: Mouse | E96: 15 | F96: 1200 | G96: 18000 | H96: Pending
... A103: TXN1181 | B103: 45305 | C103: Omicron Ltd | D103: Tablet | E103: 19 | F103: 32000 | G103: 608000 | H103: Paid
A104: TXN1182 | C104: Lambda Co | D104: Mouse | E104: 4 | F104: 1200 | G104: 4800 | H104: Paid
A105: TXN1183 | B105: 45564 | C105: Iota Ltd | D105: Webcam | E105: 17 | F105: 4500 | G105: 76500 | H105: Pending
A106: TXN1184 | B106: 45354 | C106: Gamma Inc | D106: Mouse | E106: -14 | F106: 1200 | G106: -16800 | H106: Refunded
A107: TXN1185 | B107: 45545 | C107: Nu Ventures | D107: Mouse | E107: 7 | F107: 1200 | G107: 8400 | H107: Pending
A108: TXN1186 | B108: 45386 | C108: Eta Partners | D108: Tablet | E108: 8 | F108: 32000 | G108: 512000 | H108: Refunded
A109: TXN1187 | B109: 45427 | C109: [BLANK] | D109: Laptop | E109: 18 | F109: 85000 | G109: 1530000 | H109: Refunded
A110: TXN1188 | B110: 45397 | C110: Acme Corp | D110: Webcam | E110: 19 | F110: 4500 | G110: 85500 | H110: Refunded
A111: TXN1189 | B111: 45446 | C111: Mu Holdings | D111: Keyboard | E111: 8 | F111: 3500 | G111: 28000 | H111: Paid
A112: TXN1190 | B112: 45484 | C112: Gamma Inc | D112: Tablet | E112: 2 | F112: 32000 | G112: 64000 | H112: Paid
A113: TXN1191 | B113: 45632 | C113: Xi Corp | D113: USB Hub | E113: 10 | F113: 2200 | G113: 22000 | H113: Refunded
A114: TXN1192 | B114: 45392 | C114: Theta Corp | D114: [BLANK] | E114: 8 | F114: 5000 | G114: 50000 | H114: Refunded
A115: TXN1193 | B115: 45636 | C115: Acme Corp | D115: Laptop | E115: 12 | F115: 85000 | G115: 1020000 | H115: Paid
A116: TXN1194 | B116: 45547 | C116: Zeta Group | D116: Printer | E116: 12 | F116: 18000 | G116: 216000 | H116: Failed
... A122: TXN1200 | B122: 45622 | C122: Delta Co | D122: Scanner | E122: 7 | F122: 12000 | G122: 71400 | H122: Refunded
A125: ERROR LEGEND — Colour Codes Used in This Sheet
A126: 🔴 Red cell | B126: Duplicate Transaction ID / Missing Customer or Product or Date
A127: 🟡 Yellow cell | B127: Total Amount does not equal Quantity × Price (Mismatch)
A128: 🟠 Orange cell | B128: Negative Quantity or Zero Unit Price (data-entry error)
A129: ⬜ Normal cell | B129: No error detected — value appears valid

Sheet Cleaned_Data
A1: CLEANED DATA — Formulas Applied: TRIM | IF | XLOOKUP | Corrected Totals
A2: Transaction ID | B2: Date | C2: Customer Name (TRIM) | D2: Product | E2: Quantity | F2: Unit Price ($) | G2: Corrected Total ($) | H2: Payment Status | I2: Row Flag
A3: =IF(Raw_Data!A3="","Missing",Raw_Data!A3) | B3: =IF(Raw_Data!B3="",DATE(2024,1,1),Raw_Data!B3) | C3: =TRIM(IF(Raw_Data!C3="","Unknown Customer",Raw_Data!C3)) | D3: =IF(Raw_Data!D3="","Unknown Product",Raw_Data!D3) | E3: =ABS(Raw_Data!E3) | F3: =Raw_Data!F3 | G3: =E3*F3 | H3: =IFERROR(XLOOKUP(Raw_Data!A3,Raw_Data!A:A,Raw_Data!H:H),"N/A") | I3: Clean
A4: =IF(Raw_Data!A4="","Missing",Raw_Data!A4) | B4: =IF(Raw_Data!B4="",DATE(2024,1,1),Raw_Data!B4) | C4: =TRIM(IF(Raw_Data!C4="","Unknown Customer",Raw_Data!C4)) | D4: =IF(Raw_Data!D4="","Unknown Product",Raw_Data!D4) | E4: =ABS(Raw_Data!E4) | F4: =Raw_Data!F4 | G4: =E4*F4 | H4: =IFERROR(XLOOKUP(Raw_Data!A4,Raw_Data!A:A,Raw_Data!H:H),"N/A") | I4: Clean
A5: =IF(Raw_Data!A5="","Missing",Raw_Data!A5) | B5: =IF(Raw_Data!B5="",DATE(2024,1,1),Raw_Data!B5) | C5: =TRIM(IF(Raw_Data!C5="","Unknown Customer",Raw_Data!C5)) | D5: =IF(Raw_Data!D5="","Unknown Product",Raw_Data!D5) | E5: =ABS(Raw_Data!E5) | F5: =Raw_Data!F5 | G5: =E5*F5 | H5: =IFERROR(XLOOKUP(Raw_Data!A5,Raw_Data!A:A,Raw_Data!H:H),"N/A") | I5: Fixed
A6: =IF(Raw_Data!A6="","Missing",Raw_Data!A6) | B6: =IF(Raw_Data!B6="",DATE(2024,1,1),Raw_Data!B6) | C6: =TRIM(IF(Raw_Data!C6="","Unknown Customer",Raw_Data!C6)) | D6: =IF(Raw_Data!D6="","Unknown Product",Raw_Data!D6) | E6: =ABS(Raw_Data!E6) | F6: =Raw_Data!F6 | G6: =E6*F6 | H6: =IFERROR(XLOOKUP(Raw_Data!A6,Raw_Data!A:A,Raw_Data!H:H),"N/A") | I6: Fixed
A7: =IF(Raw_Data!A7="","Missing",Raw_Data!A7) | B7: =IF(Raw_Data!B7="",DATE(2024,1,1),Raw_Data!B7) | C7: =TRIM(IF(Raw_Data!C7="","Unknown Customer",Raw_Data!C7)) | D7: =IF(Raw_Data!D7="","Unknown Product",Raw_Data!D7) | E7: =ABS(Raw_Data!E7) | F7: =Raw_Data!F7 | G7: =E7*F7 | H7: =IFERROR(XLOOKUP(Raw_Data!A7,Raw_Data!A:A,Raw_Data!H:H),"N/A") | I7: Clean
A8: =IF(Raw_Data!A8="","Missing",Raw_Data!A8) | B8: =IF(Raw_Data!B8="",DATE(2024,1,1),Raw_Data!B8) | C8: =TRIM(IF(Raw_Data!C8="","Unknown Customer",Raw_Data!C8)) | D8: =IF(Raw_Data!D8="","Unknown Product",Raw_Data!D8) | E8: =ABS(Raw_Data!E8) | F8: =Raw_Data!F8 | G8: =E8*F8 | H8: =IFERROR(XLOOKUP(Raw_Data!A8,Raw_Data!A:A,Raw_Data!H:H),"N/A") | I8: Clean
A9: =IF(Raw_Data!A9="","Missing",Raw_Data!A9) | B9: =IF(Raw_Data!B9="",DATE(2024,1,1),Raw_Data!B9) | C9: =TRIM(IF(Raw_Data!C9="","Unknown Customer",Raw_Data!C9)) | D9: =IF(Raw_Data!D9="","Unknown Product",Raw_Data!D9) | E9: =ABS(Raw_Data!E9) | F9: =Raw_Data!F9 | G9: =E9*F9 | H9: =IFERROR(XLOOKUP(Raw_Data!A9,Raw_Data!A:A,Raw_Data!H:H),"N/A") | I9: Fixed
A10: =IF(Raw_Data!A10="","Missing",Raw_Data!A10) | B10: =IF(Raw_Data!B10="",DATE(2024,1,1),Raw_Data!B10) | C10: =TRIM(IF(Raw_Data!C10="","Unknown Customer",Raw_Data!C10)) | D10: =IF(Raw_Data!D10="","Unknown Product",Raw_Data!D10) | E10: =ABS(Raw_Data!E10) | F10: =Raw_Data!F10 | G10: =E10*F10 | H10: =IFERROR(XLOOKUP(Raw_Data!A10,Raw_Data!A:A,Raw_Data!H:H),"N/A") | I10: Clean
A11: =IF(Raw_Data!A12="","Missing",Raw_Data!A12) | B11: =IF(Raw_Data!B12="",DATE(2024,1,1),Raw_Data!B12) | C11: =TRIM(IF(Raw_Data!C12="","Unknown Customer",Raw_Data!C12)) | D11: =IF(Raw_Data!D12="","Unknown Product",Raw_Data!D12) | E11: =ABS(Raw_Data!E12) | F11: =Raw_Data!F12 | G11: =E11*F11 | H11: =IFERROR(XLOOKUP(Raw_Data!A12,Raw_Data!A:A,Raw_Data!H:H),"N/A") | I11: Clean
A12: =IF(Raw_Data!A13="","Missing",Raw_Data!A13) | B12: =IF(Raw_Data!B13="",DATE(2024,1,1),Raw_Data!B13) | C12: =TRIM(IF(Raw_Data!C13="","Unknown Customer",Raw_Data!C13)) | D12: =IF(Raw_Data!D13="","Unknown Product",Raw_Data!D13) | E12: =ABS(Raw_Data!E13) | F12: =Raw_Data!F13 | G12: =E12*F12 | H12: =IFERROR(XLOOKUP(Raw_Data!A13,Raw_Data!A:A,Raw_Data!H:H),"N/A") | I12: Fixed
A13: =IF(Raw_Data!A14="","Missing",Raw_Data!A14) | B13: =IF(Raw_Data!B14="",DATE(2024,1,1),Raw_Data!B14) | C13: =TRIM(IF(Raw_Data!C14="","Unknown Customer",Raw_Data!C14)) | D13: =IF(Raw_Data!D14="","Unknown Product",Raw_Data!D14) | E13: =ABS(Raw_Data!E14) | F13: =Raw_Data!F14 | G13: =E13*F13 | H13: =IFERROR(XLOOKUP(Raw_Data!A14,Raw_Data!A:A,Raw_Data!H:H),"N/A") | I13: Fixed
A14: =IF(Raw_Data!A15="","Missing",Raw_Data!A15) | B14: =IF(Raw_Data!B15="",DATE(2024,1,1),Raw_Data!B15) | C14: =TRIM(IF(Raw_Data!C15="","Unknown Customer",Raw_Data!C15)) | D14: =IF(Raw_Data!D15="","Unknown Product",Raw_Data!D15) | E14: =ABS(Raw_Data!E15) | F14: =Raw_Data!F15 | G14: =E14*F14 | H14: =IFERROR(XLOOKUP(Raw_Data!A15,Raw_Data!A:A,Raw_Data!H:H),"N/A") | I14: Clean
A15: =IF(Raw_Data!A16="","Missing",Raw_Data!A16) | B15: =IF(Raw_Data!B16="",DATE(2024,1,1),Raw_Data!B16) | C15: =TRIM(IF(Raw_Data!C16="","Unknown Customer",Raw_Data!C16)) | D15: =IF(Raw_Data!D16="","Unknown Product",Raw_Data!D16) | E15: =ABS(Raw_Data!E16) | F15: =Raw_Data!F16 | G15: =E15*F15 | H15: =IFERROR(XLOOKUP(Raw_Data!A16,Raw_Data!A:A,Raw_Data!H:H),"N/A") | I15: Fixed
A16: =IF(Raw_Data!A17="","Missing",Raw_Data!A17) | B16: =IF(Raw_Data!B17="",DATE(2024,1,1),Raw_Data!B17) | C16: =TRIM(IF(Raw_Data!C17="","Unknown Customer",Raw_Data!C17)) | D16: =IF(Raw_Data!D17="","Unknown Product",Raw_Data!D17) | E16: =ABS(Raw_Data!E17) | F16: =Raw_Data!F17 | G16: =E16*F16 | H16: =IFERROR(XLOOKUP(Raw_Data!A17,Raw_Data!A:A,Raw_Data!H:H),"N/A") | I16: Clean
A17: =IF(Raw_Data!A18="","Missing",Raw_Data!A18) | B17: =IF(Raw_Data!B18="",DATE(2024,1,1),Raw_Data!B18) | C17: =TRIM(IF(Raw_Data!C18="","Unknown Customer",Raw_Data!C18)) | D17: =IF(Raw_Data!D18="","Unknown Product",Raw_Data!D18) | E17: =ABS(Raw_Data!E18) | F17: =Raw_Data!F18 | G17: =E17*F17 | H17: =IFERROR(XLOOKUP(Raw_Data!A18,Raw_Data!A:A,Raw_Data!H:H),"N/A") | I17: Clean
A18: =IF(Raw_Data!A19="","Missing",Raw_Data!A19) | B18: =IF(Raw_Data!B19="",DATE(2024,1,1),Raw_Data!B19) | C18: =TRIM(IF(Raw_Data!C19="","Unknown Customer",Raw_Data!C19)) | D18: =IF(Raw_Data!D19="","Unknown Product",Raw_Data!D19) | E18: =ABS(Raw_Data!E19) | F18: =Raw_Data!F19 | G18: =E18*F18 | H18: =IFERROR(XLOOKUP(Raw_Data!A19,Raw_Data!A:A,Raw_Data!H:H),"N/A") | I18: Fixed
A19: =IF(Raw_Data!A20="","Missing",Raw_Data!A20) | B19: =IF(Raw_Data!B20="",DATE(2024,1,1),Raw_Data!B20) | C19: =TRIM(IF(Raw_Data!C20="","Unknown Customer",Raw_Data!C20)) | D19: =IF(Raw_Data!D20="","Unknown Product",Raw_Data!D20) | E19: =ABS(Raw_Data!E20) | F19: =Raw_Data!F20 | G19: =E19*F19 | H19: =IFERROR(XLOOKUP(Raw_Data!A20,Raw_Data!A:A,Raw_Data!H:H),"N/A") | I19: Clean
A20: =IF(Raw_Data!A21="","Missing",Raw_Data!A21) | B20: =IF(Raw_Data!B21="",DATE(2024,1,1),Raw_Data!B21) | C20: =TRIM(IF(Raw_Data!C21="","Unknown Customer",Raw_Data!C21)) | D20: =IF(Raw_Data!D21="","Unknown Product",Raw_Data!D21) | E20: =ABS(Raw_Data!E21) | F20: =Raw_Data!F21 | G20: =E20*F20 | H20: =IFERROR(XLOOKUP(Raw_Data!A21,Raw_Data!A:A,Raw_Data!H:H),"N/A") | I20: Fixed
A21: =IF(Raw_Data!A22="","Missing",Raw_Data!A22) | B21: =IF(Raw_Data!B22="",DATE(2024,1,1),Raw_Data!B22) | C21: =TRIM(IF(Raw_Data!C22="","Unknown Customer",Raw_Data!C22)) | D21: =IF(Raw_Data!D22="","Unknown Product",Raw_Data!D22) | E21: =ABS(Raw_Data!E22) | F21: =Raw_Data!F22 | G21: =E21*F21 | H21: =IFERROR(XLOOKUP(Raw_Data!A22,Raw_Data!A:A,Raw_Data!H:H),"N/A") | I21: Clean
A22: =IF(Raw_Data!A23="","Missing",Raw_Data!A23) | B22: =IF(Raw_Data!B23="",DATE(2024,1,1),Raw_Data!B23) | C22: =TRIM(IF(Raw_Data!C23="","Unknown Customer",Raw_Data!C23)) | D22: =IF(Raw_Data!D23="","Unknown Product",Raw_Data!D23) | E22: =ABS(Raw_Data!E23) | F22: =Raw_Data!F23 | G22: =E22*F22 | H22: =IFERROR(XLOOKUP(Raw_Data!A23,Raw_Data!A:A,Raw_Data!H:H),"N/A") | I22: Clean
... A24: =IF(Raw_Data!A25="","Missing",Raw_Data!A25) | B24: =IF(Raw_Data!B25="",DATE(2024,1,1),Raw_Data!B25) | C24: =TRIM(IF(Raw_Data!C25="","Unknown Customer",Raw_Data!C25)) | D24: =IF(Raw_Data!D25="","Unknown Product",Raw_Data!D25) | E24: =ABS(Raw_Data!E25) | F24: =Raw_Data!F25 | G24: =E24*F24 | H24: =IFERROR(XLOOKUP(Raw_Data!A25,Raw_Data!A:A,Raw_Data!H:H),"N/A") | I24: Clean
A25: =IF(Raw_Data!A27="","Missing",Raw_Data!A27) | B25: =IF(Raw_Data!B27="",DATE(2024,1,1),Raw_Data!B27) | C25: =TRIM(IF(Raw_Data!C27="","Unknown Customer",Raw_Data!C27)) | D25: =IF(Raw_Data!D27="","Unknown Product",Raw_Data!D27) | E25: =ABS(Raw_Data!E27) | F25: =Raw_Data!F27 | G25: =E25*F25 | H25: =IFERROR(XLOOKUP(Raw_Data!A27,Raw_Data!A:A,Raw_Data!H:H),"N/A") | I25: Clean
A26: =IF(Raw_Data!A28="","Missing",Raw_Data!A28) | B26: =IF(Raw_Data!B28="",DATE(2024,1,1),Raw_Data!B28) | C26: =TRIM(IF(Raw_Data!C28="","Unknown Customer",Raw_Data!C28)) | D26: =IF(Raw_Data!D28="","Unknown Product",Raw_Data!D28) | E26: =ABS(Raw_Data!E28) | F26: =Raw_Data!F28 | G26: =E26*F26 | H26: =IFERROR(XLOOKUP(Raw_Data!A28,Raw_Data!A:A,Raw_Data!H:H),"N/A") | I26: Clean
A27: =IF(Raw_Data!A29="","Missing",Raw_Data!A29) | B27: =IF(Raw_Data!B29="",DATE(2024,1,1),Raw_Data!B29) | C27: =TRIM(IF(Raw_Data!C29="","Unknown Customer",Raw_Data!C29)) | D27: =IF(Raw_Data!D29="","Unknown Product",Raw_Data!D29) | E27: =ABS(Raw_Data!E29) | F27: =Raw_Data!F29 | G27: =E27*F27 | H27: =IFERROR(XLOOKUP(Raw_Data!A29,Raw_Data!A:A,Raw_Data!H:H),"N/A") | I27: Fixed
A28: =IF(Raw_Data!A30="","Missing",Raw_Data!A30) | B28: =IF(Raw_Data!B30="",DATE(2024,1,1),Raw_Data!B30) | C28: =TRIM(IF(Raw_Data!C30="","Unknown Customer",Raw_Data!C30)) | D28: =IF(Raw_Data!D30="","Unknown Product",Raw_Data!D30) | E28: =ABS(Raw_Data!E30) | F28: =Raw_Data!F30 | G28: =E28*F28 | H28: =IFERROR(XLOOKUP(Raw_Data!A30,Raw_Data!A:A,Raw_Data!H:H),"N/A") | I28: Clean
A29: =IF(Raw_Data!A32="","Missing",Raw_Data!A32) | B29: =IF(Raw_Data!B32="",DATE(2024,1,1),Raw_Data!B32) | C29: =TRIM(IF(Raw_Data!C32="","Unknown Customer",Raw_Data!C32)) | D29: =IF(Raw_Data!D32="","Unknown Product",Raw_Data!D32) | E29: =ABS(Raw_Data!E32) | F29: =Raw_Data!F32 | G29: =E29*F29 | H29: =IFERROR(XLOOKUP(Raw_Data!A32,Raw_Data!A:A,Raw_Data!H:H),"N/A") | I29: Clean
A30: =IF(Raw_Data!A33="","Missing",Raw_Data!A33) | B30: =IF(Raw_Data!B33="",DATE(2024,1,1),Raw_Data!B33) | C30: =TRIM(IF(Raw_Data!C33="","Unknown Customer",Raw_Data!C33)) | D30: =IF(Raw_Data!D33="","Unknown Product",Raw_Data!D33) | E30: =ABS(Raw_Data!E33) | F30: =Raw_Data!F33 | G30: =E30*F30 | H30: =IFERROR(XLOOKUP(Raw_Data!A33,Raw_Data!A:A,Raw_Data!H:H),"N/A") | I30: Clean
A31: =IF(Raw_Data!A34="","Missing",Raw_Data!A34) | B31: =IF(Raw_Data!B34="",DATE(2024,1,1),Raw_Data!B34) | C31: =TRIM(IF(Raw_Data!C34="","Unknown Customer",Raw_Data!C34)) | D31: =IF(Raw_Data!D34="","Unknown Product",Raw_Data!D34) | E31: =ABS(Raw_Data!E34) | F31: =Raw_Data!F34 | G31: =E31*F31 | H31: =IFERROR(XLOOKUP(Raw_Data!A34,Raw_Data!A:A,Raw_Data!H:H),"N/A") | I31: Fixed
A32: =IF(Raw_Data!A35="","Missing",Raw_Data!A35) | B32: =IF(Raw_Data!B35="",DATE(2024,1,1),Raw_Data!B35) | C32: =TRIM(IF(Raw_Data!C35="","Unknown Customer",Raw_Data!C35)) | D32: =IF(Raw_Data!D35="","Unknown Product",Raw_Data!D35) | E32: =ABS(Raw_Data!E35) | F32: =Raw_Data!F35 | G32: =E32*F32 | H32: =IFERROR(XLOOKUP(Raw_Data!A35,Raw_Data!A:A,Raw_Data!H:H),"N/A") | I32: Clean
A33: =IF(Raw_Data!A37="","Missing",Raw_Data!A37) | B33: =IF(Raw_Data!B37="",DATE(2024,1,1),Raw_Data!B37) | C33: =TRIM(IF(Raw_Data!C37="","Unknown Customer",Raw_Data!C37)) | D33: =IF(Raw_Data!D37="","Unknown Product",Raw_Data!D37) | E33: =ABS(Raw_Data!E37) | F33: =Raw_Data!F37 | G33: =E33*F33 | H33: =IFERROR(XLOOKUP(Raw_Data!A37,Raw_Data!A:A,Raw_Data!H:H),"N/A") | I33: Fixed
A34: =IF(Raw_Data!A38="","Missing",Raw_Data!A38) | B34: =IF(Raw_Data!B38="",DATE(2024,1,1),Raw_Data!B38) | C34: =TRIM(IF(Raw_Data!C38="","Unknown Customer",Raw_Data!C38)) | D34: =IF(Raw_Data!D38="","Unknown Product",Raw_Data!D38) | E34: =ABS(Raw_Data!E38) | F34: =Raw_Data!F38 | G34: =E34*F34 | H34: =IFERROR(XLOOKUP(Raw_Data!A38,Raw_Data!A:A,Raw_Data!H:H),"N/A") | I34: Clean
A35: =IF(Raw_Data!A39="","Missing",Raw_Data!A39) | B35: =IF(Raw_Data!B39="",DATE(2024,1,1),Raw_Data!B39) | C35: =TRIM(IF(Raw_Data!C39="","Unknown Customer",Raw_Data!C39)) | D35: =IF(Raw_Data!D39="","Unknown Product",Raw_Data!D39) | E35: =ABS(Raw_Data!E39) | F35: =Raw_Data!F39 | G35: =E35*F35 | H35: =IFERROR(XLOOKUP(Raw_Data!A39,Raw_Data!A:A,Raw_Data!H:H),"N/A") | I35: Fixed
A36: =IF(Raw_Data!A40="","Missing",Raw_Data!A40) | B36: =IF(Raw_Data!B40="",DATE(2024,1,1),Raw_Data!B40) | C36: =TRIM(IF(Raw_Data!C40="","Unknown Customer",Raw_Data!C40)) | D36: =IF(Raw_Data!D40="","Unknown Product",Raw_Data!D40) | E36: =ABS(Raw_Data!E40) | F36: =Raw_Data!F40 | G36: =E36*F36 | H36: =IFERROR(XLOOKUP(Raw_Data!A40,Raw_Data!A:A,Raw_Data!H:H),"N/A") | I36: Clean
A37: =IF(Raw_Data!A42="","Missing",Raw_Data!A42) | B37: =IF(Raw_Data!B42="",DATE(2024,1,1),Raw_Data!B42) | C37: =TRIM(IF(Raw_Data!C42="","Unknown Customer",Raw_Data!C42)) | D37: =IF(Raw_Data!D42="","Unknown Product",Raw_Data!D42) | E37: =ABS(Raw_Data!E42) | F37: =Raw_Data!F42 | G37: =E37*F37 | H37: =IFERROR(XLOOKUP(Raw_Data!A42,Raw_Data!A:A,Raw_Data!H:H),"N/A") | I37: Clean
A38: =IF(Raw_Data!A43="","Missing",Raw_Data!A43) | B38: =IF(Raw_Data!B43="",DATE(2024,1,1),Raw_Data!B43) | C38: =TRIM(IF(Raw_Data!C43="","Unknown Customer",Raw_Data!C43)) | D38: =IF(Raw_Data!D43="","Unknown Product",Raw_Data!D43) | E38: =ABS(Raw_Data!E43) | F38: =Raw_Data!F43 | G38: =E38*F38 | H38: =IFERROR(XLOOKUP(Raw_Data!A43,Raw_Data!A:A,Raw_Data!H:H),"N/A") | I38: Clean
A39: =IF(Raw_Data!A44="","Missing",Raw_Data!A44) | B39: =IF(Raw_Data!B44="",DATE(2024,1,1),Raw_Data!B44) | C39: =TRIM(IF(Raw_Data!C44="","Unknown Customer",Raw_Data!C44)) | D39: =IF(Raw_Data!D44="","Unknown Product",Raw_Data!D44) | E39: =ABS(Raw_Data!E44) | F39: =Raw_Data!F44 | G39: =E39*F39 | H39: =IFERROR(XLOOKUP(Raw_Data!A44,Raw_Data!A:A,Raw_Data!H:H),"N/A") | I39: Fixed
A40: =IF(Raw_Data!A45="","Missing",Raw_Data!A45) | B40: =IF(Raw_Data!B45="",DATE(2024,1,1),Raw_Data!B45) | C40: =TRIM(IF(Raw_Data!C45="","Unknown Customer",Raw_Data!C45)) | D40: =IF(Raw_Data!D45="","Unknown Product",Raw_Data!D45) | E40: =ABS(Raw_Data!E45) | F40: =Raw_Data!F45 | G40: =E40*F40 | H40: =IFERROR(XLOOKUP(Raw_Data!A45,Raw_Data!A:A,Raw_Data!H:H),"N/A") | I40: Fixed
A41: =IF(Raw_Data!A46="","Missing",Raw_Data!A46) | B41: =IF(Raw_Data!B46="",DATE(2024,1,1),Raw_Data!B46) | C41: =TRIM(IF(Raw_Data!C46="","Unknown Customer",Raw_Data!C46)) | D41: =IF(Raw_Data!D46="","Unknown Product",Raw_Data!D46) | E41: =ABS(Raw_Data!E46) | F41: =Raw_Data!F46 | G41: =E41*F41 | H41: =IFERROR(XLOOKUP(Raw_Data!A46,Raw_Data!A:A,Raw_Data!H:H),"N/A") | I41: Fixed
A42: =IF(Raw_Data!A47="","Missing",Raw_Data!A47) | B42: =IF(Raw_Data!B47="",DATE(2024,1,1),Raw_Data!B47) | C42: =TRIM(IF(Raw_Data!C47="","Unknown Customer",Raw_Data!C47)) | D42: =IF(Raw_Data!D47="","Unknown Product",Raw_Data!D47) | E42: =ABS(Raw_Data!E47) | F42: =Raw_Data!F47 | G42: =E42*F42 | H42: =IFERROR(XLOOKUP(Raw_Data!A47,Raw_Data!A:A,Raw_Data!H:H),"N/A") | I42: Fixed
A43: =IF(Raw_Data!A48="","Missing",Raw_Data!A48) | B43: =IF(Raw_Data!B48="",DATE(2024,1,1),Raw_Data!B48) | C43: =TRIM(IF(Raw_Data!C48="","Unknown Customer",Raw_Data!C48)) | D43: =IF(Raw_Data!D48="","Unknown Product",Raw_Data!D48) | E43: =ABS(Raw_Data!E48) | F43: =Raw_Data!F48 | G43: =E43*F43 | H43: =IFERROR(XLOOKUP(Raw_Data!A48,Raw_Data!A:A,Raw_Data!H:H),"N/A") | I43: Clean
A44: =IF(Raw_Data!A49="","Missing",Raw_Data!A49) | B44: =IF(Raw_Data!B49="",DATE(2024,1,1),Raw_Data!B49) | C44: =TRIM(IF(Raw_Data!C49="","Unknown Customer",Raw_Data!C49)) | D44: =IF(Raw_Data!D49="","Unknown Product",Raw_Data!D49) | E44: =ABS(Raw_Data!E49) | F44: =Raw_Data!F49 | G44: =E44*F44 | H44: =IFERROR(XLOOKUP(Raw_Data!A49,Raw_Data!A:A,Raw_Data!H:H),"N/A") | I44: Fixed
A45: =IF(Raw_Data!A50="","Missing",Raw_Data!A50) | B45: =IF(Raw_Data!B50="",DATE(2024,1,1),Raw_Data!B50) | C45: =TRIM(IF(Raw_Data!C50="","Unknown Customer",Raw_Data!C50)) | D45: =IF(Raw_Data!D50="","Unknown Product",Raw_Data!D50) | E45: =ABS(Raw_Data!E50) | F45: =Raw_Data!F50 | G45: =E45*F45 | H45: =IFERROR(XLOOKUP(Raw_Data!A50,Raw_Data!A:A,Raw_Data!H:H),"N/A") | I45: Clean
A46: =IF(Raw_Data!A52="","Missing",Raw_Data!A52) | B46: =IF(Raw_Data!B52="",DATE(2024,1,1),Raw_Data!B52) | C46: =TRIM(IF(Raw_Data!C52="","Unknown Customer",Raw_Data!C52)) | D46: =IF(Raw_Data!D52="","Unknown Product",Raw_Data!D52) | E46: =ABS(Raw_Data!E52) | F46: =Raw_Data!F52 | G46: =E46*F46 | H46: =IFERROR(XLOOKUP(Raw_Data!A52,Raw_Data!A:A,Raw_Data!H:H),"N/A") | I46: Clean
A47: =IF(Raw_Data!A53="","Missing",Raw_Data!A53) | B47: =IF(Raw_Data!B53="",DATE(2024,1,1),Raw_Data!B53) | C47: =TRIM(IF(Raw_Data!C53="","Unknown Customer",Raw_Data!C53)) | D47: =IF(Raw_Data!D53="","Unknown Product",Raw_Data!D53) | E47: =ABS(Raw_Data!E53) | F47: =Raw_Data!F53 | G47: =E47*F47 | H47: =IFERROR(XLOOKUP(Raw_Data!A53,Raw_Data!A:A,Raw_Data!H:H),"N/A") | I47: Fixed
A48: =IF(Raw_Data!A54="","Missing",Raw_Data!A54) | B48: =IF(Raw_Data!B54="",DATE(2024,1,1),Raw_Data!B54) | C48: =TRIM(IF(Raw_Data!C54="","Unknown Customer",Raw_Data!C54)) | D48: =IF(Raw_Data!D54="","Unknown Product",Raw_Data!D54) | E48: =ABS(Raw_Data!E54) | F48: =Raw_Data!F54 | G48: =E48*F48 | H48: =IFERROR(XLOOKUP(Raw_Data!A54,Raw_Data!A:A,Raw_Data!H:H),"N/A") | I48: Fixed
A49: =IF(Raw_Data!A55="","Missing",Raw_Data!A55) | B49: =IF(Raw_Data!B55="",DATE(2024,1,1),Raw_Data!B55) | C49: =TRIM(IF(Raw_Data!C55="","Unknown Customer",Raw_Data!C55)) | D49: =IF(Raw_Data!D55="","Unknown Product",Raw_Data!D55) | E49: =ABS(Raw_Data!E55) | F49: =Raw_Data!F55 | G49: =E49*F49 | H49: =IFERROR(XLOOKUP(Raw_Data!A55,Raw_Data!A:A,Raw_Data!H:H),"N/A") | I49: Clean
A50: =IF(Raw_Data!A57="","Missing",Raw_Data!A57) | B50: =IF(Raw_Data!B57="",DATE(2024,1,1),Raw_Data!B57) | C50: =TRIM(IF(Raw_Data!C57="","Unknown Customer",Raw_Data!C57)) | D50: =IF(Raw_Data!D57="","Unknown Product",Raw_Data!D57) | E50: =ABS(Raw_Data!E57) | F50: =Raw_Data!F57 | G50: =E50*F50 | H50: =IFERROR(XLOOKUP(Raw_Data!A57,Raw_Data!A:A,Raw_Data!H:H),"N/A") | I50: Clean
A51: =IF(Raw_Data!A58="","Missing",Raw_Data!A58) | B51: =IF(Raw_Data!B58="",DATE(2024,1,1),Raw_Data!B58) | C51: =TRIM(IF(Raw_Data!C58="","Unknown Customer",Raw_Data!C58)) | D51: =IF(Raw_Data!D58="","Unknown Product",Raw_Data!D58) | E51: =ABS(Raw_Data!E58) | F51: =Raw_Data!F58 | G51: =E51*F51 | H51: =IFERROR(XLOOKUP(Raw_Data!A58,Raw_Data!A:A,Raw_Data!H:H),"N/A") | I51: Fixed
A52: =IF(Raw_Data!A59="","Missing",Raw_Data!A59) | B52: =IF(Raw_Data!B59="",DATE(2024,1,1),Raw_Data!B59) | C52: =TRIM(IF(Raw_Data!C59="","Unknown Customer",Raw_Data!C59)) | D52: =IF(Raw_Data!D59="","Unknown Product",Raw_Data!D59) | E52: =ABS(Raw_Data!E59) | F52: =Raw_Data!F59 | G52: =E52*F52 | H52: =IFERROR(XLOOKUP(Raw_Data!A59,Raw_Data!A:A,Raw_Data!H:H),"N/A") | I52: Fixed
A53: =IF(Raw_Data!A60="","Missing",Raw_Data!A60) | B53: =IF(Raw_Data!B60="",DATE(2024,1,1),Raw_Data!B60) | C53: =TRIM(IF(Raw_Data!C60="","Unknown Customer",Raw_Data!C60)) | D53: =IF(Raw_Data!D60="","Unknown Product",Raw_Data!D60) | E53: =ABS(Raw_Data!E60) | F53: =Raw_Data!F60 | G53: =E53*F53 | H53: =IFERROR(XLOOKUP(Raw_Data!A60,Raw_Data!A:A,Raw_Data!H:H),"N/A") | I53: Clean
A54: =IF(Raw_Data!A62="","Missing",Raw_Data!A62) | B54: =IF(Raw_Data!B62="",DATE(2024,1,1),Raw_Data!B62) | C54: =TRIM(IF(Raw_Data!C62="","Unknown Customer",Raw_Data!C62)) | D54: =IF(Raw_Data!D62="","Unknown Product",Raw_Data!D62) | E54: =ABS(Raw_Data!E62) | F54: =Raw_Data!F62 | G54: =E54*F54 | H54: =IFERROR(XLOOKUP(Raw_Data!A62,Raw_Data!A:A,Raw_Data!H:H),"N/A") | I54: Clean
A55: =IF(Raw_Data!A63="","Missing",Raw_Data!A63) | B55: =IF(Raw_Data!B63="",DATE(2024,1,1),Raw_Data!B63) | C55: =TRIM(IF(Raw_Data!C63="","Unknown Customer",Raw_Data!C63)) | D55: =IF(Raw_Data!D63="","Unknown Product",Raw_Data!D63) | E55: =ABS(Raw_Data!E63) | F55: =Raw_Data!F63 | G55: =E55*F55 | H55: =IFERROR(XLOOKUP(Raw_Data!A63,Raw_Data!A:A,Raw_Data!H:H),"N/A") | I55: Clean
A56: =IF(Raw_Data!A64="","Missing",Raw_Data!A64) | B56: =IF(Raw_Data!B64="",DATE(2024,1,1),Raw_Data!B64) | C56: =TRIM(IF(Raw_Data!C64="","Unknown Customer",Raw_Data!C64)) | D56: =IF(Raw_Data!D64="","Unknown Product",Raw_Data!D64) | E56: =ABS(Raw_Data!E64) | F56: =Raw_Data!F64 | G56: =E56*F56 | H56: =IFERROR(XLOOKUP(Raw_Data!A64,Raw_Data!A:A,Raw_Data!H:H),"N/A") | I56: Fixed
A57: =IF(Raw_Data!A65="","Missing",Raw_Data!A65) | B57: =IF(Raw_Data!B65="",DATE(2024,1,1),Raw_Data!B65) | C57: =TRIM(IF(Raw_Data!C65="","Unknown Customer",Raw_Data!C65)) | D57: =IF(Raw_Data!D65="","Unknown Product",Raw_Data!D65) | E57: =ABS(Raw_Data!E65) | F57: =Raw_Data!F65 | G57: =E57*F57 | H57: =IFERROR(XLOOKUP(Raw_Data!A65,Raw_Data!A:A,Raw_Data!H:H),"N/A") | I57: Clean
A58: =IF(Raw_Data!A66="","Missing",Raw_Data!A66) | B58: =IF(Raw_Data!B66="",DATE(2024,1,1),Raw_Data!B66) | C58: =TRIM(IF(Raw_Data!C66="","Unknown Customer",Raw_Data!C66)) | D58: =IF(Raw_Data!D66="","Unknown Product",Raw_Data!D66) | E58: =ABS(Raw_Data!E66) | F58: =Raw_Data!F66 | G58: =E58*F58 | H58: =IFERROR(XLOOKUP(Raw_Data!A66,Raw_Data!A:A,Raw_Data!H:H),"N/A") | I58: Clean
A59: =IF(Raw_Data!A67="","Missing",Raw_Data!A67) | B59: =IF(Raw_Data!B67="",DATE(2024,1,1),Raw_Data!B67) | C59: =TRIM(IF(Raw_Data!C67="","Unknown Customer",Raw_Data!C67)) | D59: =IF(Raw_Data!D67="","Unknown Product",Raw_Data!D67) | E59: =ABS(Raw_Data!E67) | F59: =Raw_Data!F67 | G59: =E59*F59 | H59: =IFERROR(XLOOKUP(Raw_Data!A67,Raw_Data!A:A,Raw_Data!H:H),"N/A") | I59: Clean
A60: =IF(Raw_Data!A68="","Missing",Raw_Data!A68) | B60: =IF(Raw_Data!B68="",DATE(2024,1,1),Raw_Data!B68) | C60: =TRIM(IF(Raw_Data!C68="","Unknown Customer",Raw_Data!C68)) | D60: =IF(Raw_Data!D68="","Unknown Product",Raw_Data!D68) | E60: =ABS(Raw_Data!E68) | F60: =Raw_Data!F68 | G60: =E60*F60 | H60: =IFERROR(XLOOKUP(Raw_Data!A68,Raw_Data!A:A,Raw_Data!H:H),"N/A") | I60: Clean
A61: =IF(Raw_Data!A69="","Missing",Raw_Data!A69) | B61: =IF(Raw_Data!B69="",DATE(2024,1,1),Raw_Data!B69) | C61: =TRIM(IF(Raw_Data!C69="","Unknown Customer",Raw_Data!C69)) | D61: =IF(Raw_Data!D69="","Unknown Product",Raw_Data!D69) | E61: =ABS(Raw_Data!E69) | F61: =Raw_Data!F69 | G61: =E61*F61 | H61: =IFERROR(XLOOKUP(Raw_Data!A69,Raw_Data!A:A,Raw_Data!H:H),"N/A") | I61: Fixed
A62: =IF(Raw_Data!A70="","Missing",Raw_Data!A70) | B62: =IF(Raw_Data!B70="",DATE(2024,1,1),Raw_Data!B70) | C62: =TRIM(IF(Raw_Data!C70="","Unknown Customer",Raw_Data!C70)) | D62: =IF(Raw_Data!D70="","Unknown Product",Raw_Data!D70) | E62: =ABS(Raw_Data!E70) | F62: =Raw_Data!F70 | G62: =E62*F62 | H62: =IFERROR(XLOOKUP(Raw_Data!A70,Raw_Data!A:A,Raw_Data!H:H),"N/A") | I62: Clean
A63: =IF(Raw_Data!A72="","Missing",Raw_Data!A72) | B63: =IF(Raw_Data!B72="",DATE(2024,1,1),Raw_Data!B72) | C63: =TRIM(IF(Raw_Data!C72="","Unknown Customer",Raw_Data!C72)) | D63: =IF(Raw_Data!D72="","Unknown Product",Raw_Data!D72) | E63: =ABS(Raw_Data!E72) | F63: =Raw_Data!F72 | G63: =E63*F63 | H63: =IFERROR(XLOOKUP(Raw_Data!A72,Raw_Data!A:A,Raw_Data!H:H),"N/A") | I63: Clean
A64: =IF(Raw_Data!A73="","Missing",Raw_Data!A73) | B64: =IF(Raw_Data!B73="",DATE(2024,1,1),Raw_Data!B73) | C64: =TRIM(IF(Raw_Data!C73="","Unknown Customer",Raw_Data!C73)) | D64: =IF(Raw_Data!D73="","Unknown Product",Raw_Data!D73) | E64: =ABS(Raw_Data!E73) | F64: =Raw_Data!F73 | G64: =E64*F64 | H64: =IFERROR(XLOOKUP(Raw_Data!A73,Raw_Data!A:A,Raw_Data!H:H),"N/A") | I64: Clean
A65: =IF(Raw_Data!A74="","Missing",Raw_Data!A74) | B65: =IF(Raw_Data!B74="",DATE(2024,1,1),Raw_Data!B74) | C65: =TRIM(IF(Raw_Data!C74="","Unknown Customer",Raw_Data!C74)) | D65: =IF(Raw_Data!D74="","Unknown Product",Raw_Data!D74) | E65: =ABS(Raw_Data!E74) | F65: =Raw_Data!F74 | G65: =E65*F65 | H65: =IFERROR(XLOOKUP(Raw_Data!A74,Raw_Data!A:A,Raw_Data!H:H),"N/A") | I65: Fixed
A66: =IF(Raw_Data!A75="","Missing",Raw_Data!A75) | B66: =IF(Raw_Data!B75="",DATE(2024,1,1),Raw_Data!B75) | C66: =TRIM(IF(Raw_Data!C75="","Unknown Customer",Raw_Data!C75)) | D66: =IF(Raw_Data!D75="","Unknown Product",Raw_Data!D75) | E66: =ABS(Raw_Data!E75) | F66: =Raw_Data!F75 | G66: =E66*F66 | H66: =IFERROR(XLOOKUP(Raw_Data!A75,Raw_Data!A:A,Raw_Data!H:H),"N/A") | I66: Clean
A67: =IF(Raw_Data!A77="","Missing",Raw_Data!A77) | B67: =IF(Raw_Data!B77="",DATE(2024,1,1),Raw_Data!B77) | C67: =TRIM(IF(Raw_Data!C77="","Unknown Customer",Raw_Data!C77)) | D67: =IF(Raw_Data!D77="","Unknown Product",Raw_Data!D77) | E67: =ABS(Raw_Data!E77) | F67: =Raw_Data!F77 | G67: =E67*F67 | H67: =IFERROR(XLOOKUP(Raw_Data!A77,Raw_Data!A:A,Raw_Data!H:H),"N/A") | I67: Fixed
A68: =IF(Raw_Data!A78="","Missing",Raw_Data!A78) | B68: =IF(Raw_Data!B78="",DATE(2024,1,1),Raw_Data!B78) | C68: =TRIM(IF(Raw_Data!C78="","Unknown Customer",Raw_Data!C78)) | D68: =IF(Raw_Data!D78="","Unknown Product",Raw_Data!D78) | E68: =ABS(Raw_Data!E78) | F68: =Raw_Data!F78 | G68: =E68*F68 | H68: =IFERROR(XLOOKUP(Raw_Data!A78,Raw_Data!A:A,Raw_Data!H:H),"N/A") | I68: Clean
A69: =IF(Raw_Data!A79="","Missing",Raw_Data!A79) | B69: =IF(Raw_Data!B79="",DATE(2024,1,1),Raw_Data!B79) | C69: =TRIM(IF(Raw_Data!C79="","Unknown Customer",Raw_Data!C79)) | D69: =IF(Raw_Data!D79="","Unknown Product",Raw_Data!D79) | E69: =ABS(Raw_Data!E79) | F69: =Raw_Data!F79 | G69: =E69*F69 | H69: =IFERROR(XLOOKUP(Raw_Data!A79,Raw_Data!A:A,Raw_Data!H:H),"N/A") | I69: Fixed
A70: =IF(Raw_Data!A80="","Missing",Raw_Data!A80) | B70: =IF(Raw_Data!B80="",DATE(2024,1,1),Raw_Data!B80) | C70: =TRIM(IF(Raw_Data!C80="","Unknown Customer",Raw_Data!C80)) | D70: =IF(Raw_Data!D80="","Unknown Product",Raw_Data!D80) | E70: =ABS(Raw_Data!E80) | F70: =Raw_Data!F80 | G70: =E70*F70 | H70: =IFERROR(XLOOKUP(Raw_Data!A80,Raw_Data!A:A,Raw_Data!H:H),"N/A") | I70: Fixed
A71: =IF(Raw_Data!A81="","Missing",Raw_Data!A81) | B71: =IF(Raw_Data!B81="",DATE(2024,1,1),Raw_Data!B81) | C71: =TRIM(IF(Raw_Data!C81="","Unknown Customer",Raw_Data!C81)) | D71: =IF(Raw_Data!D81="","Unknown Product",Raw_Data!D81) | E71: =ABS(Raw_Data!E81) | F71: =Raw_Data!F81 | G71: =E71*F71 | H71: =IFERROR(XLOOKUP(Raw_Data!A81,Raw_Data!A:A,Raw_Data!H:H),"N/A") | I71: Clean
A72: =IF(Raw_Data!A82="","Missing",Raw_Data!A82) | B72: =IF(Raw_Data!B82="",DATE(2024,1,1),Raw_Data!B82) | C72: =TRIM(IF(Raw_Data!C82="","Unknown Customer",Raw_Data!C82)) | D72: =IF(Raw_Data!D82="","Unknown Product",Raw_Data!D82) | E72: =ABS(Raw_Data!E82) | F72: =Raw_Data!F82 | G72: =E72*F72 | H72: =IFERROR(XLOOKUP(Raw_Data!A82,Raw_Data!A:A,Raw_Data!H:H),"N/A") | I72: Clean
A73: =IF(Raw_Data!A83="","Missing",Raw_Data!A83) | B73: =IF(Raw_Data!B83="",DATE(2024,1,1),Raw_Data!B83) | C73: =TRIM(IF(Raw_Data!C83="","Unknown Customer",Raw_Data!C83)) | D73: =IF(Raw_Data!D83="","Unknown Product",Raw_Data!D83) | E73: =ABS(Raw_Data!E83) | F73: =Raw_Data!F83 | G73: =E73*F73 | H73: =IFERROR(XLOOKUP(Raw_Data!A83,Raw_Data!A:A,Raw_Data!H:H),"N/A") | I73: Clean
A74: =IF(Raw_Data!A84="","Missing",Raw_Data!A84) | B74: =IF(Raw_Data!B84="",DATE(2024,1,1),Raw_Data!B84) | C74: =TRIM(IF(Raw_Data!C84="","Unknown Customer",Raw_Data!C84)) | D74: =IF(Raw_Data!D84="","Unknown Product",Raw_Data!D84) | E74: =ABS(Raw_Data!E84) | F74: =Raw_Data!F84 | G74: =E74*F74 | H74: =IFERROR(XLOOKUP(Raw_Data!A84,Raw_Data!A:A,Raw_Data!H:H),"N/A") | I74: Fixed
A75: =IF(Raw_Data!A85="","Missing",Raw_Data!A85) | B75: =IF(Raw_Data!B85="",DATE(2024,1,1),Raw_Data!B85) | C75: =TRIM(IF(Raw_Data!C85="","Unknown Customer",Raw_Data!C85)) | D75: =IF(Raw_Data!D85="","Unknown Product",Raw_Data!D85) | E75: =ABS(Raw_Data!E85) | F75: =Raw_Data!F85 | G75: =E75*F75 | H75: =IFERROR(XLOOKUP(Raw_Data!A85,Raw_Data!A:A,Raw_Data!H:H),"N/A") | I75: Fixed
A76: =IF(Raw_Data!A86="","Missing",Raw_Data!A86) | B76: =IF(Raw_Data!B86="",DATE(2024,1,1),Raw_Data!B86) | C76: =TRIM(IF(Raw_Data!C86="","Unknown Customer",Raw_Data!C86)) | D76: =IF(Raw_Data!D86="","Unknown Product",Raw_Data!D86) | E76: =ABS(Raw_Data!E86) | F76: =Raw_Data!F86 | G76: =E76*F76 | H76: =IFERROR(XLOOKUP(Raw_Data!A86,Raw_Data!A:A,Raw_Data!H:H),"N/A") | I76: Clean
A77: =IF(Raw_Data!A87="","Missing",Raw_Data!A87) | B77: =IF(Raw_Data!B87="",DATE(2024,1,1),Raw_Data!B87) | C77: =TRIM(IF(Raw_Data!C87="","Unknown Customer",Raw_Data!C87)) | D77: =IF(Raw_Data!D87="","Unknown Product",Raw_Data!D87) | E77: =ABS(Raw_Data!E87) | F77: =Raw_Data!F87 | G77: =E77*F77 | H77: =IFERROR(XLOOKUP(Raw_Data!A87,Raw_Data!A:A,Raw_Data!H:H),"N/A") | I77: Clean
A78: =IF(Raw_Data!A88="","Missing",Raw_Data!A88) | B78: =IF(Raw_Data!B88="",DATE(2024,1,1),Raw_Data!B88) | C78: =TRIM(IF(Raw_Data!C88="","Unknown Customer",Raw_Data!C88)) | D78: =IF(Raw_Data!D88="","Unknown Product",Raw_Data!D88) | E78: =ABS(Raw_Data!E88) | F78: =Raw_Data!F88 | G78: =E78*F78 | H78: =IFERROR(XLOOKUP(Raw_Data!A88,Raw_Data!A:A,Raw_Data!H:H),"N/A") | I78: Clean
... A112: =IF(Raw_Data!A122="","Missing",Raw_Data!A122) | B112: =IF(Raw_Data!B122="",DATE(2024,1,1),Raw_Data!B122) | C112: =TRIM(IF(Raw_Data!C122="","Unknown Customer",Raw_Data!C122)) | D112: =IF(Raw_Data!D122="","Unknown Product",Raw_Data!D122) | E112: =ABS(Raw_Data!E122) | F112: =Raw_Data!F122 | G112: =E112*F112 | H112: =IFERROR(XLOOKUP(Raw_Data!A122,Raw_Data!A:A,Raw_Data!H:H),"N/A") | I112: Fixed
A113: TOTAL (Cleaned) | G113: =SUM(G3:G112)
A115: FORMULAS USED IN THIS SHEET — For Interview Reference
A116: Column | B116: Formula Used | C116: Purpose
A117: Column C | B117: =TRIM(IF(Raw_Data!C2="","Unknown Customer",Raw_Data!C2)) | C117: Removes spaces + fills blanks
A118: Column D | B118: =IF(Raw_Data!D2="","Unknown Product",Raw_Data!D2) | C118: Fills blank product names
A119: Column E | B119: =ABS(Raw_Data!E2) | C119: Converts negative qty to positive
A120: Column G | B120: =E2*F2 | C120: Always recalculates correct total
A121: Column H | B121: =IFERROR(XLOOKUP(A2,Raw_Data!A:A,Raw_Data!H:H),"N/A") | C121: XLOOKUP to fetch status
A122: Column B | B122: =IF(Raw_Data!B2="",DATE(2024,1,1),Raw_Data!B2) | C122: Fills missing dates with default

Sheet Validation_Checks
A1: VALIDATION CHECKS — Duplicate | Missing Value | Amount Mismatch | Additional Flags
A2: Transaction ID | B2: Date | C2: Customer Name | D2: Product | E2: Quantity | F2: Unit Price ($) | G2: Total Amount ($) | H2: Payment Status | I2: Duplicate Check | J2: Missing Value Check | K2: Amount Mismatch | L2: Additional Flag
A3: TXN1081 | B3: 45376 | C3: Eta Partners | D3: Tablet | E3: 10 | F3: 32000 | G3: 320000 | H3: Refunded | I3: =IF(COUNTIF($A$3:$A$122,A3)>1,"Duplicate","OK") | J3: =IF(OR(A3="",B3="",C3="",D3=""),"Missing","OK") | K3: =IF(ABS(G3-(E3*F3))>0.01,"Mismatch","OK") | L3: OK
A4: TXN1082 | B4: 45402 | C4: Nu Ventures | D4: Printer | E4: 17 | F4: 18000 | G4: 306000 | H4: Paid | I4: =IF(COUNTIF($A$3:$A$122,A4)>1,"Duplicate","OK") | J4: =IF(OR(A4="",B4="",C4="",D4=""),"Missing","OK") | K4: =IF(ABS(G4-(E4*F4))>0.01,"Mismatch","OK") | L4: OK
A5: TXN1083 | B5: 45550 | C5: Iota Ltd | D5: Mouse | E5: 1 | F5: 1200 | G5: 1320 | H5: Pending | I5: =IF(COUNTIF($A$3:$A$122,A5)>1,"Duplicate","OK") | J5: =IF(OR(A5="",B5="",C5="",D5=""),"Missing","OK") | K5: =IF(ABS(G5-(E5*F5))>0.01,"Mismatch","OK") | L5: OK
A6: TXN1020 | B6: 45511 | C6: Beta Ltd | D6: Keyboard | E6: 8 | F6: 3500 | G6: 28000 | H6: Paid | I6: =IF(COUNTIF($A$3:$A$122,A6)>1,"Duplicate","OK") | J6: =IF(OR(A6="",B6="",C6="",D6=""),"Missing","OK") | K6: =IF(ABS(G6-(E6*F6))>0.01,"Mismatch","OK") | L6: OK
A7: TXN1085 | B7: 45647 | C7: Acme Corp | D7: Tablet | E7: 14 | F7: 32000 | G7: 448000 | H7: Refunded | I7: =IF(COUNTIF($A$3:$A$122,A7)>1,"Duplicate","OK") | J7: =IF(OR(A7="",B7="",C7="",D7=""),"Missing","OK") | K7: =IF(ABS(G7-(E7*F7))>0.01,"Mismatch","OK") | L7: OK
A8: TXN1086 | B8: 45309 | C8: Zeta Group | D8: Scanner | E8: 16 | F8: 12000 | G8: 192000 | H8: Paid | I8: =IF(COUNTIF($A$3:$A$122,A8)>1,"Duplicate","OK") | J8: =IF(OR(A8="",B8="",C8="",D8=""),"Missing","OK") | K8: =IF(ABS(G8-(E8*F8))>0.01,"Mismatch","OK") | L8: OK
A9: TXN1087 | B9: 45624 | C9: [BLANK] | D9: Webcam | E9: 1 | F9: 4500 | G9: 4500 | H9: Paid | I9: =IF(COUNTIF($A$3:$A$122,A9)>1,"Duplicate","OK") | J9: =IF(OR(A9="",B9="",C9="",D9=""),"Missing","OK") | K9: =IF(ABS(G9-(E9*F9))>0.01,"Mismatch","OK") | L9: OK
A10: TXN1088 | B10: 45337 | C10: Beta Ltd | D10: Laptop | E10: 15 | F10: 85000 | G10: 1275000 | H10: Paid | I10: =IF(COUNTIF($A$3:$A$122,A10)>1,"Duplicate","OK") | J10: =IF(OR(A10="",B10="",C10="",D10=""),"Missing","OK") | K10: =IF(ABS(G10-(E10*F10))>0.01,"Mismatch","OK") | L10: OK
A11: TXN1020 | B11: 45467 | C11: Eta Partners | D11: Printer | E11: 5 | F11: 18000 | G11: 90000 | H11: Paid | I11: =IF(COUNTIF($A$3:$A$122,A11)>1,"Duplicate","OK") | J11: =IF(OR(A11="",B11="",C11="",D11=""),"Missing","OK") | K11: =IF(ABS(G11-(E11*F11))>0.01,"Mismatch","OK") | L11: OK
A12: TXN1090 | B12: 45632 | C12: Acme Corp | D12: Printer | E12: 8 | F12: 18000 | G12: 144000 | H12: Paid | I12: =IF(COUNTIF($A$3:$A$122,A12)>1,"Duplicate","OK") | J12: =IF(OR(A12="",B12="",C12="",D12=""),"Missing","OK") | K12: =IF(ABS(G12-(E12*F12))>0.01,"Mismatch","OK") | L12: OK
A13: TXN1091 | B13: 45393 | C13: Delta Co | D13: USB Hub | E13: 3 | F13: 2200 | G13: 7260 | H13: Refunded | I13: =IF(COUNTIF($A$3:$A$122,A13)>1,"Duplicate","OK") | J13: =IF(OR(A13="",B13="",C13="",D13=""),"Missing","OK") | K13: =IF(ABS(G13-(E13*F13))>0.01,"Mismatch","OK") | L13: OK
A14: TXN1092 | B14: 45578 | C14: Xi Corp | D14: [BLANK] | E14: 13 | F14: 5000 | G14: 65000 | H14: Paid | I14: =IF(COUNTIF($A$3:$A$122,A14)>1,"Duplicate","OK") | J14: =IF(OR(A14="",B14="",C14="",D14=""),"Missing","OK") | K14: =IF(ABS(G14-(E14*F14))>0.01,"Mismatch","OK") | L14: OK
... A23: TXN1101 | B23: 45511 | C23: Zeta Group | D23: Keyboard | E23: 2 | F23: 3500 | G23: 7000 | H23: Paid | I23: =IF(COUNTIF($A$3:$A$122,A23)>1,"Duplicate","OK") | J23: =IF(OR(A23="",B23="",C23="",D23=""),"Missing","OK") | K23: =IF(ABS(G23-(E23*F23))>0.01,"Mismatch","OK") | L23: OK
A24: TXN1102 | C24: Eta Partners | D24: Keyboard | E24: 19 | F24: 3500 | G24: 66500 | H24: Paid | I24: =IF(COUNTIF($A$3:$A$122,A24)>1,"Duplicate","OK") | J24: =IF(OR(A24="",B24="",C24="",D24=""),"Missing","OK") | K24: =IF(ABS(G24-(E24*F24))>0.01,"Mismatch","OK") | L24: OK
A25: TXN1103 | B25: 45469 | C25: Theta Corp | D25: Scanner | E25: 13 | F25: 12000 | G25: 156000 | H25: Paid | I25: =IF(COUNTIF($A$3:$A$122,A25)>1,"Duplicate","OK") | J25: =IF(OR(A25="",B25="",C25="",D25=""),"Missing","OK") | K25: =IF(ABS(G25-(E25*F25))>0.01,"Mismatch","OK") | L25: OK
A26: TXN1005 | B26: 45375 | C26: Iota Ltd | D26: Monitor | E26: 15 | F26: 22000 | G26: 330000 | H26: Failed | I26: =IF(COUNTIF($A$3:$A$122,A26)>1,"Duplicate","OK") | J26: =IF(OR(A26="",B26="",C26="",D26=""),"Missing","OK") | K26: =IF(ABS(G26-(E26*F26))>0.01,"Mismatch","OK") | L26: OK
A27: TXN1105 | B27: 45539 | C27: Acme Corp | D27: Headphones | E27: 2 | F27: 8500 | G27: 17000 | H27: Pending | I27: =IF(COUNTIF($A$3:$A$122,A27)>1,"Duplicate","OK") | J27: =IF(OR(A27="",B27="",C27="",D27=""),"Missing","OK") | K27: =IF(ABS(G27-(E27*F27))>0.01,"Mismatch","OK") | L27: OK
A28: TXN1106 | B28: 45629 | C28: Epsilon LLC | D28: Laptop | E28: 14 | F28: 85000 | G28: 1190000 | H28: Paid | I28: =IF(COUNTIF($A$3:$A$122,A28)>1,"Duplicate","OK") | J28: =IF(OR(A28="",B28="",C28="",D28=""),"Missing","OK") | K28: =IF(ABS(G28-(E28*F28))>0.01,"Mismatch","OK") | L28: OK
A29: TXN1107 | B29: 45379 | C29: [BLANK] | D29: Tablet | E29: 3 | F29: 32000 | G29: 144000 | H29: Paid | I29: =IF(COUNTIF($A$3:$A$122,A29)>1,"Duplicate","OK") | J29: =IF(OR(A29="",B29="",C29="",D29=""),"Missing","OK") | K29: =IF(ABS(G29-(E29*F29))>0.01,"Mismatch","OK") | L29: OK
A30: TXN1108 | B30: 45369 | C30: Mu Holdings | D30: Printer | E30: 2 | F30: 18000 | G30: 36000 | H30: Pending | I30: =IF(COUNTIF($A$3:$A$122,A30)>1,"Duplicate","OK") | J30: =IF(OR(A30="",B30="",C30="",D30=""),"Missing","OK") | K30: =IF(ABS(G30-(E30*F30))>0.01,"Mismatch","OK") | L30: OK
A31: TXN1005 | B31: 45624 | C31: Iota Ltd | D31: Printer | E31: 1 | F31: 18000 | G31: 18000 | H31: Paid | I31: =IF(COUNTIF($A$3:$A$122,A31)>1,"Duplicate","OK") | J31: =IF(OR(A31="",B31="",C31="",D31=""),"Missing","OK") | K31: =IF(ABS(G31-(E31*F31))>0.01,"Mismatch","OK") | L31: OK
A32: TXN1110 | B32: 45479 | C32: Nu Ventures | D32: Keyboard | E32: 12 | F32: 3500 | G32: 42000 | H32: Failed | I32: =IF(COUNTIF($A$3:$A$122,A32)>1,"Duplicate","OK") | J32: =IF(OR(A32="",B32="",C32="",D32=""),"Missing","OK") | K32: =IF(ABS(G32-(E32*F32))>0.01,"Mismatch","OK") | L32: OK
A33: TXN1111 | B33: 45540 | C33: Kappa Inc | D33: Printer | E33: 10 | F33: 18000 | G33: 180000 | H33: Paid | I33: =IF(COUNTIF($A$3:$A$122,A33)>1,"Duplicate","OK") | J33: =IF(OR(A33="",B33="",C33="",D33=""),"Missing","OK") | K33: =IF(ABS(G33-(E33*F33))>0.01,"Mismatch","OK") | L33: OK
A34: TXN1112 | B34: 45565 | C34: Kappa Inc | D34: [BLANK] | E34: 9 | F34: 5000 | G34: 45000 | H34: Paid | I34: =IF(COUNTIF($A$3:$A$122,A34)>1,"Duplicate","OK") | J34: =IF(OR(A34="",B34="",C34="",D34=""),"Missing","OK") | K34: =IF(ABS(G34-(E34*F34))>0.01,"Mismatch","OK") | L34: OK
A35: TXN1113 | B35: 45297 | C35: Eta Partners | D35: Keyboard | E35: 1 | F35: 3500 | G35: 3500 | H35: Pending | I35: =IF(COUNTIF($A$3:$A$122,A35)>1,"Duplicate","OK") | J35: =IF(OR(A35="",B35="",C35="",D35=""),"Missing","OK") | K35: =IF(ABS(G35-(E35*F35))>0.01,"Mismatch","OK") | L35: OK
A36: TXN1020 | B36: 45458 | C36: Lambda Co | D36: Mouse | E36: 19 | F36: 1200 | G36: 22800 | H36: Failed | I36: =IF(COUNTIF($A$3:$A$122,A36)>1,"Duplicate","OK") | J36: =IF(OR(A36="",B36="",C36="",D36=""),"Missing","OK") | K36: =IF(ABS(G36-(E36*F36))>0.01,"Mismatch","OK") | L36: OK
... A43: TXN1121 | B43: 45601 | C43: Mu Holdings | D43: Scanner | E43: 2 | F43: 12000 | G43: 24000 | H43: Paid | I43: =IF(COUNTIF($A$3:$A$122,A43)>1,"Duplicate","OK") | J43: =IF(OR(A43="",B43="",C43="",D43=""),"Missing","OK") | K43: =IF(ABS(G43-(E43*F43))>0.01,"Mismatch","OK") | L43: OK
A44: TXN1122 | C44: Eta Partners | D44: Printer | E44: 3 | F44: 18000 | G44: 54000 | H44: Failed | I44: =IF(COUNTIF($A$3:$A$122,A44)>1,"Duplicate","OK") | J44: =IF(OR(A44="",B44="",C44="",D44=""),"Missing","OK") | K44: =IF(ABS(G44-(E44*F44))>0.01,"Mismatch","OK") | L44: OK
A45: TXN1123 | B45: 45582 | C45: Gamma Inc | D45: Mouse | E45: 9 | F45: 1200 | G45: 13500 | H45: Pending | I45: =IF(COUNTIF($A$3:$A$122,A45)>1,"Duplicate","OK") | J45: =IF(OR(A45="",B45="",C45="",D45=""),"Missing","OK") | K45: =IF(ABS(G45-(E45*F45))>0.01,"Mismatch","OK") | L45: OK
A46: TXN1001 | B46: 45417 | C46: Eta Partners | D46: Keyboard | E46: 10 | F46: 3500 | G46: 35000 | H46: Pending | I46: =IF(COUNTIF($A$3:$A$122,A46)>1,"Duplicate","OK") | J46: =IF(OR(A46="",B46="",C46="",D46=""),"Missing","OK") | K46: =IF(ABS(G46-(E46*F46))>0.01,"Mismatch","OK") | L46: OK
A47: TXN1125 | B47: 45549 | C47: Nu Ventures | D47: Scanner | E47: -16 | F47: 12000 | G47: -192000 | H47: Paid | I47: =IF(COUNTIF($A$3:$A$122,A47)>1,"Duplicate","OK") | J47: =IF(OR(A47="",B47="",C47="",D47=""),"Missing","OK") | K47: =IF(ABS(G47-(E47*F47))>0.01,"Mismatch","OK") | L47: Negative Qty
A48: TXN1126 | B48: 45571 | C48: Kappa Inc | D48: Laptop | E48: 17 | F48: 85000 | G48: 1445000 | H48: Pending | I48: =IF(COUNTIF($A$3:$A$122,A48)>1,"Duplicate","OK") | J48: =IF(OR(A48="",B48="",C48="",D48=""),"Missing","OK") | K48: =IF(ABS(G48-(E48*F48))>0.01,"Mismatch","OK") | L48: OK
A49: TXN1127 | B49: 45556 | C49: [BLANK] | D49: Headphones | E49: 10 | F49: 8500 | G49: 85000 | H49: Paid | I49: =IF(COUNTIF($A$3:$A$122,A49)>1,"Duplicate","OK") | J49: =IF(OR(A49="",B49="",C49="",D49=""),"Missing","OK") | K49: =IF(ABS(G49-(E49*F49))>0.01,"Mismatch","OK") | L49: OK
A50: TXN1128 | B50: 45324 | C50: Kappa Inc | D50: Webcam | E50: 7 | F50: 4500 | G50: 31500 | H50: Pending | I50: =IF(COUNTIF($A$3:$A$122,A50)>1,"Duplicate","OK") | J50: =IF(OR(A50="",B50="",C50="",D50=""),"Missing","OK") | K50: =IF(ABS(G50-(E50*F50))>0.01,"Mismatch","OK") | L50: OK
A51: TXN1001 | B51: 45454 | C51: Lambda Co | D51: Tablet | E51: 4 | F51: 32000 | G51: 128000 | H51: Paid | I51: =IF(COUNTIF($A$3:$A$122,A51)>1,"Duplicate","OK") | J51: =IF(OR(A51="",B51="",C51="",D51=""),"Missing","OK") | K51: =IF(ABS(G51-(E51*F51))>0.01,"Mismatch","OK") | L51: OK
A52: TXN1130 | B52: 45625 | C52: Beta Ltd | D52: Printer | E52: 17 | F52: 18000 | G52: 306000 | H52: Paid | I52: =IF(COUNTIF($A$3:$A$122,A52)>1,"Duplicate","OK") | J52: =IF(OR(A52="",B52="",C52="",D52=""),"Missing","OK") | K52: =IF(ABS(G52-(E52*F52))>0.01,"Mismatch","OK") | L52: OK
A53: TXN1131 | B53: 45640 | C53: Lambda Co | D53: Printer | E53: 16 | F53: 18000 | G53: 172800 | H53: Failed | I53: =IF(COUNTIF($A$3:$A$122,A53)>1,"Duplicate","OK") | J53: =IF(OR(A53="",B53="",C53="",D53=""),"Missing","OK") | K53: =IF(ABS(G53-(E53*F53))>0.01,"Mismatch","OK") | L53: OK
A54: TXN1132 | B54: 45497 | C54: Beta Ltd | D54: [BLANK] | E54: 8 | F54: 5000 | G54: 40000 | H54: Paid | I54: =IF(COUNTIF($A$3:$A$122,A54)>1,"Duplicate","OK") | J54: =IF(OR(A54="",B54="",C54="",D54=""),"Missing","OK") | K54: =IF(ABS(G54-(E54*F54))>0.01,"Mismatch","OK") | L54: OK
A55: TXN1133 | B55: 45316 | C55: Lambda Co | D55: Tablet | E55: 2 | F55: 32000 | G55: 64000 | H55: Paid | I55: =IF(COUNTIF($A$3:$A$122,A55)>1,"Duplicate","OK") | J55: =IF(OR(A55="",B55="",C55="",D55=""),"Missing","OK") | K55: =IF(ABS(G55-(E55*F55))>0.01,"Mismatch","OK") | L55: OK
A56: TXN1010 | B56: 45652 | C56: Kappa Inc | D56: Tablet | E56: 14 | F56: 32000 | G56: 448000 | H56: Refunded | I56: =IF(COUNTIF($A$3:$A$122,A56)>1,"Duplicate","OK") | J56: =IF(OR(A56="",B56="",C56="",D56=""),"Missing","OK") | K56: =IF(ABS(G56-(E56*F56))>0.01,"Mismatch","OK") | L56: OK
... A63: TXN1141 | B63: 45395 | C63: Epsilon LLC | D63: Tablet | E63: 5 | F63: 32000 | G63: 160000 | H63: Paid | I63: =IF(COUNTIF($A$3:$A$122,A63)>1,"Duplicate","OK") | J63: =IF(OR(A63="",B63="",C63="",D63=""),"Missing","OK") | K63: =IF(ABS(G63-(E63*F63))>0.01,"Mismatch","OK") | L63: OK
A64: TXN1142 | C64: Iota Ltd | D64: Keyboard | E64: 3 | F64: 3500 | G64: 10500 | H64: Pending | I64: =IF(COUNTIF($A$3:$A$122,A64)>1,"Duplicate","OK") | J64: =IF(OR(A64="",B64="",C64="",D64=""),"Missing","OK") | K64: =IF(ABS(G64-(E64*F64))>0.01,"Mismatch","OK") | L64: OK
A65: TXN1143 | B65: 45609 | C65: Eta Partners | D65: Printer | E65: 4 | F65: 18000 | G65: 72000 | H65: Paid | I65: =IF(COUNTIF($A$3:$A$122,A65)>1,"Duplicate","OK") | J65: =IF(OR(A65="",B65="",C65="",D65=""),"Missing","OK") | K65: =IF(ABS(G65-(E65*F65))>0.01,"Mismatch","OK") | L65: OK
A66: TXN1015 | B66: 45397 | C66: Lambda Co | D66: Webcam | E66: 12 | F66: 4500 | G66: 54000 | H66: Paid | I66: =IF(COUNTIF($A$3:$A$122,A66)>1,"Duplicate","OK") | J66: =IF(OR(A66="",B66="",C66="",D66=""),"Missing","OK") | K66: =IF(ABS(G66-(E66*F66))>0.01,"Mismatch","OK") | L66: OK
A67: TXN1145 | B67: 45425 | C67: Beta Ltd | D67: Laptop | E67: 11 | F67: 85000 | G67: 935000 | H67: Pending | I67: =IF(COUNTIF($A$3:$A$122,A67)>1,"Duplicate","OK") | J67: =IF(OR(A67="",B67="",C67="",D67=""),"Missing","OK") | K67: =IF(ABS(G67-(E67*F67))>0.01,"Mismatch","OK") | L67: OK
A68: TXN1146 | B68: 45370 | C68: Omicron Ltd | D68: Scanner | E68: 7 | F68: 12000 | G68: 84000 | H68: Paid | I68: =IF(COUNTIF($A$3:$A$122,A68)>1,"Duplicate","OK") | J68: =IF(OR(A68="",B68="",C68="",D68=""),"Missing","OK") | K68: =IF(ABS(G68-(E68*F68))>0.01,"Mismatch","OK") | L68: OK
A69: TXN1147 | B69: 45598 | C69: [BLANK] | D69: Headphones | E69: 13 | F69: 8500 | G69: 93925 | H69: Failed | I69: =IF(COUNTIF($A$3:$A$122,A69)>1,"Duplicate","OK") | J69: =IF(OR(A69="",B69="",C69="",D69=""),"Missing","OK") | K69: =IF(ABS(G69-(E69*F69))>0.01,"Mismatch","OK") | L69: OK
A70: TXN1148 | B70: 45531 | C70: Eta Partners | D70: Tablet | E70: 15 | F70: 32000 | G70: 480000 | H70: Pending | I70: =IF(COUNTIF($A$3:$A$122,A70)>1,"Duplicate","OK") | J70: =IF(OR(A70="",B70="",C70="",D70=""),"Missing","OK") | K70: =IF(ABS(G70-(E70*F70))>0.01,"Mismatch","OK") | L70: OK
A71: TXN1005 | B71: 45633 | C71: Eta Partners | D71: USB Hub | E71: 9 | F71: 2200 | G71: 19800 | H71: Paid | I71: =IF(COUNTIF($A$3:$A$122,A71)>1,"Duplicate","OK") | J71: =IF(OR(A71="",B71="",C71="",D71=""),"Missing","OK") | K71: =IF(ABS(G71-(E71*F71))>0.01,"Mismatch","OK") | L71: OK
A72: TXN1150 | B72: 45388 | C72: Delta Co | D72: Laptop | E72: 12 | F72: 85000 | G72: 1020000 | H72: Pending | I72: =IF(COUNTIF($A$3:$A$122,A72)>1,"Duplicate","OK") | J72: =IF(OR(A72="",B72="",C72="",D72=""),"Missing","OK") | K72: =IF(ABS(G72-(E72*F72))>0.01,"Mismatch","OK") | L72: OK
A73: TXN1151 | B73: 45301 | C73: Beta Ltd | D73: Scanner | E73: 19 | F73: 12000 | G73: 228000 | H73: Paid | I73: =IF(COUNTIF($A$3:$A$122,A73)>1,"Duplicate","OK") | J73: =IF(OR(A73="",B73="",C73="",D73=""),"Missing","OK") | K73: =IF(ABS(G73-(E73*F73))>0.01,"Mismatch","OK") | L73: OK
A74: TXN1152 | B74: 45495 | C74: Kappa Inc | D74: [BLANK] | E74: 15 | F74: 5000 | G74: 75000 | H74: Refunded | I74: =IF(COUNTIF($A$3:$A$122,A74)>1,"Duplicate","OK") | J74: =IF(OR(A74="",B74="",C74="",D74=""),"Missing","OK") | K74: =IF(ABS(G74-(E74*F74))>0.01,"Mismatch","OK") | L74: OK
A75: TXN1153 | B75: 45414 | C75: Acme Corp | D75: Scanner | E75: 5 | F75: 12000 | G75: 60000 | H75: Paid | I75: =IF(COUNTIF($A$3:$A$122,A75)>1,"Duplicate","OK") | J75: =IF(OR(A75="",B75="",C75="",D75=""),"Missing","OK") | K75: =IF(ABS(G75-(E75*F75))>0.01,"Mismatch","OK") | L75: OK
A76: TXN1010 | B76: 45389 | C76: Theta Corp | D76: Webcam | E76: 1 | F76: 4500 | G76: 4500 | H76: Pending | I76: =IF(COUNTIF($A$3:$A$122,A76)>1,"Duplicate","OK") | J76: =IF(OR(A76="",B76="",C76="",D76=""),"Missing","OK") | K76: =IF(ABS(G76-(E76*F76))>0.01,"Mismatch","OK") | L76: OK
... A83: TXN1161 | B83: 45533 | C83: Lambda Co | D83: Webcam | E83: 5 | F83: 4500 | G83: 22500 | H83: Pending | I83: =IF(COUNTIF($A$3:$A$122,A83)>1,"Duplicate","OK") | J83: =IF(OR(A83="",B83="",C83="",D83=""),"Missing","OK") | K83: =IF(ABS(G83-(E83*F83))>0.01,"Mismatch","OK") | L83: OK
A84: TXN1162 | C84: Gamma Inc | D84: Webcam | E84: 10 | F84: 4500 | G84: 45000 | H84: Pending | I84: =IF(COUNTIF($A$3:$A$122,A84)>1,"Duplicate","OK") | J84: =IF(OR(A84="",B84="",C84="",D84=""),"Missing","OK") | K84: =IF(ABS(G84-(E84*F84))>0.01,"Mismatch","OK") | L84: OK
A85: TXN1163 | B85: 45619 | C85: Lambda Co | D85: Laptop | E85: 3 | F85: 85000 | G85: 318750 | H85: Paid | I85: =IF(COUNTIF($A$3:$A$122,A85)>1,"Duplicate","OK") | J85: =IF(OR(A85="",B85="",C85="",D85=""),"Missing","OK") | K85: =IF(ABS(G85-(E85*F85))>0.01,"Mismatch","OK") | L85: OK
A86: TXN1164 | B86: 45387 | C86: Iota Ltd | D86: Monitor | E86: 7 | F86: 22000 | G86: 154000 | H86: Pending | I86: =IF(COUNTIF($A$3:$A$122,A86)>1,"Duplicate","OK") | J86: =IF(OR(A86="",B86="",C86="",D86=""),"Missing","OK") | K86: =IF(ABS(G86-(E86*F86))>0.01,"Mismatch","OK") | L86: OK
A87: TXN1165 | B87: 45430 | C87: Zeta Group | D87: Laptop | E87: 6 | F87: 85000 | G87: 510000 | H87: Paid | I87: =IF(COUNTIF($A$3:$A$122,A87)>1,"Duplicate","OK") | J87: =IF(OR(A87="",B87="",C87="",D87=""),"Missing","OK") | K87: =IF(ABS(G87-(E87*F87))>0.01,"Mismatch","OK") | L87: OK
A88: TXN1166 | B88: 45591 | C88: Theta Corp | D88: Headphones | E88: 13 | F88: 8500 | G88: 110500 | H88: Paid | I88: =IF(COUNTIF($A$3:$A$122,A88)>1,"Duplicate","OK") | J88: =IF(OR(A88="",B88="",C88="",D88=""),"Missing","OK") | K88: =IF(ABS(G88-(E88*F88))>0.01,"Mismatch","OK") | L88: OK
A89: TXN1167 | B89: 45308 | C89: [BLANK] | D89: Monitor | E89: 8 | F89: 22000 | G89: 176000 | H89: Pending | I89: =IF(COUNTIF($A$3:$A$122,A89)>1,"Duplicate","OK") | J89: =IF(OR(A89="",B89="",C89="",D89=""),"Missing","OK") | K89: =IF(ABS(G89-(E89*F89))>0.01,"Mismatch","OK") | L89: OK
A90: TXN1168 | B90: 45567 | C90: Epsilon LLC | D90: Tablet | E90: 7 | F90: 32000 | G90: 224000 | H90: Paid | I90: =IF(COUNTIF($A$3:$A$122,A90)>1,"Duplicate","OK") | J90: =IF(OR(A90="",B90="",C90="",D90=""),"Missing","OK") | K90: =IF(ABS(G90-(E90*F90))>0.01,"Mismatch","OK") | L90: OK
A91: TXN1169 | B91: 45560 | C91: Eta Partners | D91: Monitor | E91: 11 | F91: 0 | G91: 0 | H91: Paid | I91: =IF(COUNTIF($A$3:$A$122,A91)>1,"Duplicate","OK") | J91: =IF(OR(A91="",B91="",C91="",D91=""),"Missing","OK") | K91: =IF(ABS(G91-(E91*F91))>0.01,"Mismatch","OK") | L91: Zero Price
A92: TXN1170 | B92: 45401 | C92: Iota Ltd | D92: Laptop | E92: 12 | F92: 85000 | G92: 1020000 | H92: Paid | I92: =IF(COUNTIF($A$3:$A$122,A92)>1,"Duplicate","OK") | J92: =IF(OR(A92="",B92="",C92="",D92=""),"Missing","OK") | K92: =IF(ABS(G92-(E92*F92))>0.01,"Mismatch","OK") | L92: OK
A93: TXN1171 | B93: 45302 | C93: Mu Holdings | D93: Webcam | E93: 16 | F93: 4500 | G93: 144000 | H93: Paid | I93: =IF(COUNTIF($A$3:$A$122,A93)>1,"Duplicate","OK") | J93: =IF(OR(A93="",B93="",C93="",D93=""),"Missing","OK") | K93: =IF(ABS(G93-(E93*F93))>0.01,"Mismatch","OK") | L93: OK
A94: TXN1172 | B94: 45518 | C94: Nu Ventures | D94: [BLANK] | E94: 1 | F94: 5000 | G94: 5000 | H94: Pending | I94: =IF(COUNTIF($A$3:$A$122,A94)>1,"Duplicate","OK") | J94: =IF(OR(A94="",B94="",C94="",D94=""),"Missing","OK") | K94: =IF(ABS(G94-(E94*F94))>0.01,"Mismatch","OK") | L94: OK
A95: TXN1173 | B95: 45639 | C95: Acme Corp | D95: Mouse | E95: 20 | F95: 1200 | G95: 24000 | H95: Paid | I95: =IF(COUNTIF($A$3:$A$122,A95)>1,"Duplicate","OK") | J95: =IF(OR(A95="",B95="",C95="",D95=""),"Missing","OK") | K95: =IF(ABS(G95-(E95*F95))>0.01,"Mismatch","OK") | L95: OK
A96: TXN1174 | B96: 45450 | C96: Eta Partners | D96: Mouse | E96: 15 | F96: 1200 | G96: 18000 | H96: Pending | I96: =IF(COUNTIF($A$3:$A$122,A96)>1,"Duplicate","OK") | J96: =IF(OR(A96="",B96="",C96="",D96=""),"Missing","OK") | K96: =IF(ABS(G96-(E96*F96))>0.01,"Mismatch","OK") | L96: OK
... A103: TXN1181 | B103: 45305 | C103: Omicron Ltd | D103: Tablet | E103: 19 | F103: 32000 | G103: 608000 | H103: Paid | I103: =IF(COUNTIF($A$3:$A$122,A103)>1,"Duplicate","OK") | J103: =IF(OR(A103="",B103="",C103="",D103=""),"Missing","OK") | K103: =IF(ABS(G103-(E103*F103))>0.01,"Mismatch","OK") | L103: OK
A104: TXN1182 | C104: Lambda Co | D104: Mouse | E104: 4 | F104: 1200 | G104: 4800 | H104: Paid | I104: =IF(COUNTIF($A$3:$A$122,A104)>1,"Duplicate","OK") | J104: =IF(OR(A104="",B104="",C104="",D104=""),"Missing","OK") | K104: =IF(ABS(G104-(E104*F104))>0.01,"Mismatch","OK") | L104: OK
A105: TXN1183 | B105: 45564 | C105: Iota Ltd | D105: Webcam | E105: 17 | F105: 4500 | G105: 76500 | H105: Pending | I105: =IF(COUNTIF($A$3:$A$122,A105)>1,"Duplicate","OK") | J105: =IF(OR(A105="",B105="",C105="",D105=""),"Missing","OK") | K105: =IF(ABS(G105-(E105*F105))>0.01,"Mismatch","OK") | L105: OK
A106: TXN1184 | B106: 45354 | C106: Gamma Inc | D106: Mouse | E106: -14 | F106: 1200 | G106: -16800 | H106: Refunded | I106: =IF(COUNTIF($A$3:$A$122,A106)>1,"Duplicate","OK") | J106: =IF(OR(A106="",B106="",C106="",D106=""),"Missing","OK") | K106: =IF(ABS(G106-(E106*F106))>0.01,"Mismatch","OK") | L106: Negative Qty
A107: TXN1185 | B107: 45545 | C107: Nu Ventures | D107: Mouse | E107: 7 | F107: 1200 | G107: 8400 | H107: Pending | I107: =IF(COUNTIF($A$3:$A$122,A107)>1,"Duplicate","OK") | J107: =IF(OR(A107="",B107="",C107="",D107=""),"Missing","OK") | K107: =IF(ABS(G107-(E107*F107))>0.01,"Mismatch","OK") | L107: OK
A108: TXN1186 | B108: 45386 | C108: Eta Partners | D108: Tablet | E108: 8 | F108: 32000 | G108: 512000 | H108: Refunded | I108: =IF(COUNTIF($A$3:$A$122,A108)>1,"Duplicate","OK") | J108: =IF(OR(A108="",B108="",C108="",D108=""),"Missing","OK") | K108: =IF(ABS(G108-(E108*F108))>0.01,"Mismatch","OK") | L108: OK
A109: TXN1187 | B109: 45427 | C109: [BLANK] | D109: Laptop | E109: 18 | F109: 85000 | G109: 1530000 | H109: Refunded | I109: =IF(COUNTIF($A$3:$A$122,A109)>1,"Duplicate","OK") | J109: =IF(OR(A109="",B109="",C109="",D109=""),"Missing","OK") | K109: =IF(ABS(G109-(E109*F109))>0.01,"Mismatch","OK") | L109: OK
A110: TXN1188 | B110: 45397 | C110: Acme Corp | D110: Webcam | E110: 19 | F110: 4500 | G110: 85500 | H110: Refunded | I110: =IF(COUNTIF($A$3:$A$122,A110)>1,"Duplicate","OK") | J110: =IF(OR(A110="",B110="",C110="",D110=""),"Missing","OK") | K110: =IF(ABS(G110-(E110*F110))>0.01,"Mismatch","OK") | L110: OK
A111: TXN1189 | B111: 45446 | C111: Mu Holdings | D111: Keyboard | E111: 8 | F111: 3500 | G111: 28000 | H111: Paid | I111: =IF(COUNTIF($A$3:$A$122,A111)>1,"Duplicate","OK") | J111: =IF(OR(A111="",B111="",C111="",D111=""),"Missing","OK") | K111: =IF(ABS(G111-(E111*F111))>0.01,"Mismatch","OK") | L111: OK
A112: TXN1190 | B112: 45484 | C112: Gamma Inc | D112: Tablet | E112: 2 | F112: 32000 | G112: 64000 | H112: Paid | I112: =IF(COUNTIF($A$3:$A$122,A112)>1,"Duplicate","OK") | J112: =IF(OR(A112="",B112="",C112="",D112=""),"Missing","OK") | K112: =IF(ABS(G112-(E112*F112))>0.01,"Mismatch","OK") | L112: OK
A113: TXN1191 | B113: 45632 | C113: Xi Corp | D113: USB Hub | E113: 10 | F113: 2200 | G113: 22000 | H113: Refunded | I113: =IF(COUNTIF($A$3:$A$122,A113)>1,"Duplicate","OK") | J113: =IF(OR(A113="",B113="",C113="",D113=""),"Missing","OK") | K113: =IF(ABS(G113-(E113*F113))>0.01,"Mismatch","OK") | L113: OK
A114: TXN1192 | B114: 45392 | C114: Theta Corp | D114: [BLANK] | E114: 8 | F114: 5000 | G114: 50000 | H114: Refunded | I114: =IF(COUNTIF($A$3:$A$122,A114)>1,"Duplicate","OK") | J114: =IF(OR(A114="",B114="",C114="",D114=""),"Missing","OK") | K114: =IF(ABS(G114-(E114*F114))>0.01,"Mismatch","OK") | L114: OK
A115: TXN1193 | B115: 45636 | C115: Acme Corp | D115: Laptop | E115: 12 | F115: 85000 | G115: 1020000 | H115: Paid | I115: =IF(COUNTIF($A$3:$A$122,A115)>1,"Duplicate","OK") | J115: =IF(OR(A115="",B115="",C115="",D115=""),"Missing","OK") | K115: =IF(ABS(G115-(E115*F115))>0.01,"Mismatch","OK") | L115: OK
A116: TXN1194 | B116: 45547 | C116: Zeta Group | D116: Printer | E116: 12 | F116: 18000 | G116: 216000 | H116: Failed | I116: =IF(COUNTIF($A$3:$A$122,A116)>1,"Duplicate","OK") | J116: =IF(OR(A116="",B116="",C116="",D116=""),"Missing","OK") | K116: =IF(ABS(G116-(E116*F116))>0.01,"Mismatch","OK") | L116: OK
... A122: TXN1200 | B122: 45622 | C122: Delta Co | D122: Scanner | E122: 7 | F122: 12000 | G122: 71400 | H122: Refunded | I122: =IF(COUNTIF($A$3:$A$122,A122)>1,"Duplicate","OK") | J122: =IF(OR(A122="",B122="",C122="",D122=""),"Missing","OK") | K122: =IF(ABS(G122-(E122*F122))>0.01,"Mismatch","OK") | L122: OK
A125: VALIDATION FORMULAS — Exact formulas used in columns I, J, K
A126: Check Name | B126: Formula
A127: Col I — Duplicate Check | B127: =IF(COUNTIF($A$3:$A$122,A3)>1,"Duplicate","OK")
A128: Col J — Missing Value Check | B128: =IF(OR(A3="",B3="",C3="",D3=""),"Missing","OK")
A129: Col K — Amount Mismatch | B129: =IF(ABS(G3-(E3*F3))>0.01,"Mismatch","OK")

Sheet Reconciliation_Summary
B2: RECONCILIATION SUMMARY — Data Quality KPI Report
B4: DATA QUALITY KPIs
B5: KPI Metric | C5: Formula Used | D5: Result
B6: Total Raw Records | C6: =COUNTA(Raw_Data!A:A)-1 | D6: =COUNTA(Raw_Data!A:A)-1
B7: Duplicate Records | C7: =COUNTIF(Validation_Checks!I:I,"Duplicate") | D7: =COUNTIF(Validation_Checks!I3:I122,"Duplicate")
B8: Missing Value Records | C8: =COUNTIF(Validation_Checks!J:J,"Missing") | D8: =COUNTIF(Validation_Checks!J3:J122,"Missing")
B9: Amount Mismatch Records | C9: =COUNTIF(Validation_Checks!K:K,"Mismatch") | D9: =COUNTIF(Validation_Checks!K3:K122,"Mismatch")
B10: Additional Flags (Neg Qty/Zero Prc) | C10: =COUNTIF(Validation_Checks!L:L,"<>OK") | D10: =COUNTIF(Validation_Checks!L3:L122,"<>OK")
B11: Total Error Records | C11: =C7+C8+C9+C10 | D11: =C7+C8+C9+C10
B12: Clean Records (Estimated) | C12: =C6-C11 | D12: =C6-C11
B13: Data Quality Score (%) | C13: =IFERROR(C12/C6,0) | D13: =IFERROR(C12/C6,0)
B14: Error Rate (%) | C14: =IFERROR(C11/C6,0) | D14: =IFERROR(C11/C6,0)
B17: PAYMENT STATUS BREAKDOWN
B18: Status | C18: Count Formula | D18: Count
B19: Paid | C19: =COUNTIF(Raw_Data!H:H,"Paid") | D19: 63
B20: Pending | C20: =COUNTIF(Raw_Data!H:H,"Pending") | D20: 30
B21: Failed | C21: =COUNTIF(Raw_Data!H:H,"Failed") | D21: 9
B22: Refunded | C22: =COUNTIF(Raw_Data!H:H,"Refunded") | D22: 18
B25: FINANCIAL RECONCILIATION
B26: Metric | C26: Formula | D26: Amount ($)
B27: Raw Total (as recorded) | C27: =SUM(Raw_Data!G:G) | D27: 23649385
B28: Corrected Total (Qty×Price) | C28: =SUMPRODUCT(Raw_Data!E3:E122,Raw_Data!F3:F122) | D28: 22984600
B29: Variance ($) | C29: =D27-D28 | D29: 664785
B30: Variance (%) | C30: =IFERROR(D29/D28,0) | D30: 0.028923062
B33: ERRORS BY PRODUCT
B34: Product | C34: Total Records | D34: Error Records
B35: Headphones | C35: 8 | D35: 3
B36: Keyboard | C36: 10 | D36: 4
B37: Laptop | C37: 11 | D37: 2
B38: Monitor | C38: 9 | D38: 7
B39: Mouse | C39: 9 | D39: 5
B40: Printer | C40: 17 | D40: 8
B41: Scanner | C41: 13 | D41: 5
B42: Tablet | C42: 17 | D42: 5
B43: USB Hub | C43: 7 | D43: 5
B44: Unknown | C44: 6 | D44: 6
B45: Webcam | C45: 13 | D45: 5

Sheet Dashboard
B2: 📊 DATA VALIDATION & RECONCILIATION DASHBOARD
B4: Total Records | C4: Total Errors | D4: Clean Records | E4: Data Quality Score
B5: 120 | C5: 55 | D5: 65 | E5: 0.54166667
B7: All raw transactions | C7: Across all error types | D7: Error-free records | E7: % of records clean
B8: Duplicates | C8: Missing Values | D8: Mismatches | E8: Other Flags
B9: 14 | C9: 23 | D9: 18 | E9: 5
B11: Duplicate TXN IDs | C11: Blank fields | D11: Amt ≠ Qty×Price | E11: Neg Qty / Zero Price
B13: CHART DATA TABLES
B14: Error Type | C14: Count | E14: Payment Status | F14: Count | H14: Product | I14: Total Sales ($)
B15: Duplicates | C15: 14 | E15: Paid | F15: 63 | H15: Laptop | I15: 10710000
B16: Missing Values | C16: 23 | E16: Pending | F16: 30 | H16: Tablet | I16: 4640000
B17: Mismatches | C17: 18 | E17: Failed | F17: 9 | H17: Printer | I17: 2772000
B18: Other Flags | C18: 5 | E18: Refunded | F18: 18 | H18: Scanner | I18: 1560000
H19: Monitor | I19: 1386000
H20: Webcam | I20: 639000
H21: Headphones | I21: 476000
H22: Keyboard | I22: 294000
H23: Unknown | I23: 270000
H24: USB Hub | I24: 158400
H25: Mouse | I25: 79200
B60: 📌 KEY INSIGHTS — Data Validation & Reconciliation Analysis
B61: 📊 45.8% of records (55 out of 120) contain at least one data quality issue requiring corrective action.
B62: 🔁 Most common error is 'Missing Values' — systematic data entry or integration issue; source system controls recommended.
B63: 💰 Financial variance of $664,785 found between raw totals and corrected (Qty×Price) values — critical for P&L accuracy.
B64: ⏳ 30 transactions (25.0%) remain PENDING — follow-up required to improve cash collection velocity.
B65: ✅ After cleaning, 65 records (54.2%) are validated and ready for downstream reporting.
B66: 📈 Applying TRIM, IF, and ABS formulas removed whitespace, filled blanks, and fixed sign errors — improving model reliability.
B67: 🏷️ Laptop and Tablet generate highest sales but appear in multiple mismatch rows — source system pricing review recommended.
